[
  {
    "title": "China’s Infrastructure Bond Drought Weighs on Investment",
    "link": "https://www.bloomberg.com/news/articles/2025-12-23/china-trapped-in-investment-slump-as-infrastructure-bonds-dry-up",
    "source": "Bloomberg Markets",
    "category": "Markets & Finance",
    "published": "Tue, 23 Dec 2025 22:00:00 GMT",
    "thumbnail": "https://assets.bwbx.io/images/users/iqjWHBFdfxIU/i_wGhFj6C6.E/v3/1200x-1.png",
    "importance": 45,
    "importanceLabel": "Medium",
    "updated_at": "2025-12-24T02:54:55.184458"
  },
  {
    "title": "English councils warned against adopting four-day week",
    "link": "https://www.bbc.com/news/articles/cgl6j8n04eno?at_medium=RSS&at_campaign=rss",
    "source": "BBC News",
    "category": "Markets & Finance",
    "published": "Tue, 23 Dec 2025 02:44:50 GMT",
    "thumbnail": "https://ichef.bbci.co.uk/ace/standard/240/cpsprodpb/bf8a/live/4f9bf400-dfe9-11f0-b67b-690eb873de1b.jpg",
    "importance": 45,
    "importanceLabel": "Medium",
    "updated_at": "2025-12-24T02:54:55.942755"
  },
  {
    "title": "Won Jumps After Korea Vows ‘Strong Determination’ Over Currency",
    "link": "https://www.bloomberg.com/news/articles/2025-12-24/korea-says-fx-market-will-soon-see-government-s-determination",
    "source": "Bloomberg Markets",
    "category": "Markets & Finance",
    "published": "Wed, 24 Dec 2025 00:17:41 GMT",
    "thumbnail": "https://assets.bwbx.io/images/users/iqjWHBFdfxIU/i.frD0FjIQE0/v1/1200x-1.jpg",
    "importance": 40,
    "importanceLabel": "Medium",
    "updated_at": "2025-12-24T02:54:55.184310"
  },
  {
    "title": "Copper Set For Best Year Since 2009 After December Surge",
    "link": "https://www.bloomberg.com/news/articles/2025-12-24/copper-set-for-best-year-since-2009-after-december-surge",
    "source": "Bloomberg Markets",
    "category": "Markets & Finance",
    "published": "Wed, 24 Dec 2025 02:38:38 GMT",
    "thumbnail": "https://assets.bwbx.io/images/users/iqjWHBFdfxIU/iwpB2i2BDUPA/v1/1200x-1.jpg",
    "importance": 40,
    "importanceLabel": "Medium",
    "updated_at": "2025-12-24T02:54:55.184352"
  },
  {
    "title": "Asian Stocks Advance on Tech, Commodities Rally: Markets Wrap",
    "link": "https://www.bloomberg.com/news/articles/2025-12-23/stock-market-today-dow-s-p-live-updates",
    "source": "Bloomberg Markets",
    "category": "Markets & Finance",
    "published": "Tue, 23 Dec 2025 22:32:33 GMT",
    "thumbnail": "https://assets.bwbx.io/images/users/iqjWHBFdfxIU/iAsEFZ_lfPGk/v1/1200x-1.jpg",
    "importance": 40,
    "importanceLabel": "Medium",
    "updated_at": "2025-12-24T02:54:55.184492"
  },
  {
    "title": "Colombia Uses Emergency Powers to Hike Tax on Banks and the Rich",
    "link": "https://www.bloomberg.com/news/articles/2025-12-24/colombia-uses-emergency-powers-to-hike-tax-on-banks-and-the-rich",
    "source": "Bloomberg Markets",
    "category": "Markets & Finance",
    "published": "Wed, 24 Dec 2025 01:02:19 GMT",
    "thumbnail": "https://assets.bwbx.io/images/users/iqjWHBFdfxIU/iIIpfKxSweiQ/v0/1200x-1.jpg",
    "importance": 40,
    "importanceLabel": "Medium",
    "updated_at": "2025-12-24T02:54:55.184586"
  },
  {
    "title": "Call of Duty co-creator Vince Zampella dies in California car crash",
    "link": "https://www.bbc.com/news/articles/cx25rled0ylo?at_medium=RSS&at_campaign=rss",
    "source": "BBC News",
    "category": "Markets & Finance",
    "published": "Tue, 23 Dec 2025 10:04:47 GMT",
    "thumbnail": "https://ichef.bbci.co.uk/ace/standard/240/cpsprodpb/09cf/live/c3c06b50-df84-11f0-b89f-11674143d4d8.jpg",
    "importance": 40,
    "importanceLabel": "Medium",
    "updated_at": "2025-12-24T02:54:55.942772"
  },
  {
    "title": "Cooling Labor Market and Elevated Inflation Stoke Fed Divisions on Rate Cuts",
    "link": "https://www.nytimes.com/2025/12/12/business/economy/fed-rate-decision-dissents.html",
    "source": "NYT > Business > Economy",
    "category": "Global Economy",
    "published": "Fri, 12 Dec 2025 15:28:19 +0000",
    "thumbnail": "https://static01.nyt.com/images/2025/12/12/multimedia/12dc-fed-vtwc/12dc-fed-vtwc-mediumSquareAt3X.jpg",
    "importance": 40,
    "importanceLabel": "Medium",
    "updated_at": "2025-12-24T02:54:56.353155"
  },
  {
    "title": "Yemen’s Warring Sides Agree to Largest Prisoner Swap in a Decade of Fighting",
    "link": "https://www.nytimes.com/2025/12/23/world/middleeast/yemen-houthis-prisoner-exchange.html",
    "source": "NYT > World News",
    "category": "Geopolitics",
    "published": "Tue, 23 Dec 2025 15:52:08 +0000",
    "thumbnail": "https://static01.nyt.com/images/2025/12/23/multimedia/23int-yemen-houthi-ljwc/23int-yemen-houthi-ljwc-mediumSquareAt3X.jpg",
    "importance": 40,
    "importanceLabel": "Medium",
    "updated_at": "2025-12-24T02:54:56.469273"
  },
  {
    "title": "Libyan Military’s Chief of Staff and 4 Others Are Killed in Plane Crash in Turkey",
    "link": "https://www.nytimes.com/2025/12/23/world/middleeast/libya-general-plane-crash-turkey.html",
    "source": "NYT > World News",
    "category": "Geopolitics",
    "published": "Tue, 23 Dec 2025 22:53:57 +0000",
    "thumbnail": "https://static01.nyt.com/images/2025/12/23/multimedia/23int-libya-jet-1-bjmc/23int-libya-jet-1-bjmc-mediumSquareAt3X.jpg",
    "importance": 40,
    "importanceLabel": "Medium",
    "updated_at": "2025-12-24T02:54:56.469585"
  },
  {
    "title": "‘We don’t hear murmurs… when data disappoints’: CEA Nageswaran hits out at GDP critics",
    "link": "https://indianexpress.com/article/business/cea-nageswaran-hits-out-at-gdp-critics-says-no-questions-raised-when-growth-disappoints-10434793/",
    "source": "Business | The Indian Express",
    "category": "Business",
    "published": "Tue, 23 Dec 2025 09:54:31 +0000",
    "thumbnail": "https://images.indianexpress.com/2025/12/nageswaran-1.jpg",
    "importance": 40,
    "importanceLabel": "Medium",
    "updated_at": "2025-12-24T02:54:57.620105"
  },
  {
    "title": "China’s Comac on Track to Miss C919 Delivery Target by Half",
    "link": "https://www.bloomberg.com/news/articles/2025-12-23/china-s-comac-on-track-to-miss-c919-delivery-target-by-half",
    "source": "Bloomberg Markets",
    "category": "Markets & Finance",
    "published": "Tue, 23 Dec 2025 23:00:00 GMT",
    "thumbnail": "https://assets.bwbx.io/images/users/iqjWHBFdfxIU/iX1kt0NJqYeQ/v0/1200x-1.jpg",
    "importance": 35,
    "importanceLabel": "Medium",
    "updated_at": "2025-12-24T02:54:55.184790"
  },
  {
    "title": "Gold and Silver Rise to Records on Rate-Cut Bets, Global Risks",
    "link": "https://www.bloomberg.com/news/articles/2025-12-22/gold-climbs-to-record-on-us-rate-cut-bets-and-geopolitical-risk",
    "source": "Bloomberg Markets",
    "category": "Markets & Finance",
    "published": "Mon, 22 Dec 2025 23:36:52 GMT",
    "thumbnail": "https://assets.bwbx.io/images/users/iqjWHBFdfxIU/ih3zJQa0_Npg/v1/1200x-1.jpg",
    "importance": 35,
    "importanceLabel": "Medium",
    "updated_at": "2025-12-24T02:54:55.184942"
  },
  {
    "title": "Who are the frontrunners for the top Fed job?",
    "link": "https://www.bbc.com/news/articles/c4g907zekllo?at_medium=RSS&at_campaign=rss",
    "source": "BBC News",
    "category": "Markets & Finance",
    "published": "Tue, 23 Dec 2025 06:01:14 GMT",
    "thumbnail": "https://ichef.bbci.co.uk/ace/standard/240/cpsprodpb/900e/live/aa175510-df57-11f0-aae2-2191c0e48a3b.jpg",
    "importance": 35,
    "importanceLabel": "Medium",
    "updated_at": "2025-12-24T02:54:55.942657"
  },
  {
    "title": "Amazon blocks 1,800 job applications from suspected North Korean agents",
    "link": "https://www.bbc.com/news/articles/c3e0kw80wwzo?at_medium=RSS&at_campaign=rss",
    "source": "BBC News",
    "category": "Markets & Finance",
    "published": "Tue, 23 Dec 2025 02:49:45 GMT",
    "thumbnail": "https://ichef.bbci.co.uk/ace/standard/240/cpsprodpb/7a77/live/f29f1a40-dfa0-11f0-a643-15fd7b194a0b.jpg",
    "importance": 35,
    "importanceLabel": "Medium",
    "updated_at": "2025-12-24T02:54:55.942674"
  },
  {
    "title": "US pauses offshore wind projects over security concerns",
    "link": "https://www.bbc.com/news/articles/cd74lyr094vo?at_medium=RSS&at_campaign=rss",
    "source": "BBC News",
    "category": "Markets & Finance",
    "published": "Mon, 22 Dec 2025 21:02:43 GMT",
    "thumbnail": "https://ichef.bbci.co.uk/ace/standard/240/cpsprodpb/50ac/live/93cbbcb0-df61-11f0-aae2-2191c0e48a3b.jpg",
    "importance": 35,
    "importanceLabel": "Medium",
    "updated_at": "2025-12-24T02:54:55.942738"
  },
  {
    "title": "RBI Governor Expects ‘Long Period of Low Policy Rates’ for India",
    "link": "https://www.bloomberg.com/news/articles/2025-12-23/rbi-governor-expects-long-period-of-low-policy-rates-for-india",
    "source": "Bloomberg Economics",
    "category": "Global Economy",
    "published": "Tue, 23 Dec 2025 14:10:53 GMT",
    "thumbnail": "https://assets.bwbx.io/images/users/iqjWHBFdfxIU/iPRK63VtT8jM/v1/1200x-1.jpg",
    "importance": 35,
    "importanceLabel": "Medium",
    "updated_at": "2025-12-24T02:54:56.069446"
  },
  {
    "title": "Colombia Declares ‘Economic Emergency’ After Tax Rises Nixed",
    "link": "https://www.bloomberg.com/news/articles/2025-12-23/colombia-declares-economic-emergency-after-tax-rises-nixed",
    "source": "Bloomberg Economics",
    "category": "Global Economy",
    "published": "Tue, 23 Dec 2025 13:33:19 GMT",
    "thumbnail": "https://assets.bwbx.io/images/users/iqjWHBFdfxIU/iG2hHe_xRIIk/v0/1200x-1.jpg",
    "importance": 35,
    "importanceLabel": "Medium",
    "updated_at": "2025-12-24T02:54:56.069488"
  },
  {
    "title": "US Immigration Policy and the Normalization of Military Rule in Myanmar",
    "link": "https://thediplomat.com/2025/12/us-immigration-policy-and-the-normalization-of-military-rule-in-myanmar/",
    "source": "The Diplomat",
    "category": "Geopolitics",
    "published": "Tue, 23 Dec 2025 14:19:00 +0900",
    "thumbnail": "https://images.thediplomat.com/v1/td-list-l-2/2025/12/thediplomat_2025-12-23-142918.jpg",
    "importance": 35,
    "importanceLabel": "Medium",
    "updated_at": "2025-12-24T02:54:56.621149"
  },
  {
    "title": "Beyond the Fighting: Leadership and Scams in the Thailand-Cambodia Crisis",
    "link": "https://thediplomat.com/2025/12/beyond-the-fighting-leadership-and-scams-in-the-thailand-cambodia-crisis/",
    "source": "The Diplomat",
    "category": "Geopolitics",
    "published": "Tue, 23 Dec 2025 07:09:00 +0900",
    "thumbnail": "https://images.thediplomat.com/v1/td-list-l-2/2025/12/thediplomat_2025-12-23-071300.jpg",
    "importance": 35,
    "importanceLabel": "Medium",
    "updated_at": "2025-12-24T02:54:56.621254"
  },
  {
    "title": "Myanmar’s Military Prepares to Enact Its Election Plan",
    "link": "https://thediplomat.com/2025/12/myanmars-military-prepares-to-enact-its-election-plan/",
    "source": "The Diplomat",
    "category": "Geopolitics",
    "published": "Tue, 23 Dec 2025 09:44:00 +0900",
    "thumbnail": "https://images.thediplomat.com/v1/td-list-l-2/2025/12/thediplomat_2025-12-23-095339.jpg",
    "importance": 35,
    "importanceLabel": "Medium",
    "updated_at": "2025-12-24T02:54:56.621300"
  },
  {
    "title": "After the Subsidies: EVs and Lessons from China’s Industrial Policy",
    "link": "https://thediplomat.com/2025/12/after-the-subsidies-evs-and-lessons-from-chinas-industrial-policy/",
    "source": "The Diplomat",
    "category": "Geopolitics",
    "published": "Tue, 23 Dec 2025 03:57:00 +0900",
    "thumbnail": "https://images.thediplomat.com/v1/td-list-l-2/2025/12/thediplomat_2025-12-23-040221.jpg",
    "importance": 35,
    "importanceLabel": "Medium",
    "updated_at": "2025-12-24T02:54:56.621424"
  },
  {
    "title": "Court sends 2014 Slender Man attacker back to mental health institution after failed escape bid",
    "link": "https://indianexpress.com/article/world/court-sends-2014-slender-man-attacker-back-to-mental-health-institution-after-failed-escape-bid-10435703/",
    "source": "World | The Indian Express",
    "category": "Geopolitics",
    "published": "Tue, 23 Dec 2025 19:56:01 +0000",
    "thumbnail": "https://images.indianexpress.com/2025/12/morgan-geyser.jpg",
    "importance": 35,
    "importanceLabel": "Medium",
    "updated_at": "2025-12-24T02:54:57.045845"
  },
  {
    "title": "Who was Vince Zampella? Co-creator of ‘Call of Duty’, dies at 55 in California car crash",
    "link": "https://indianexpress.com/article/world/who-was-vince-zampella-co-creator-of-call-of-duty-dies-at-55-in-california-car-crash-10434738/",
    "source": "World | The Indian Express",
    "category": "Geopolitics",
    "published": "Tue, 23 Dec 2025 09:37:43 +0000",
    "thumbnail": "https://images.indianexpress.com/2025/12/Vince-Zampella.jpg",
    "importance": 35,
    "importanceLabel": "Medium",
    "updated_at": "2025-12-24T02:54:57.046225"
  },
  {
    "title": "RRP Semiconductor’s stock price surges 55,000 per cent, triggering regulatory concerns",
    "link": "https://indianexpress.com/article/business/rrp-semiconductors-stock-price-surges-55000-per-cent-triggering-regulatory-concerns-10430772/",
    "source": "Business | The Indian Express",
    "category": "Business",
    "published": "Sat, 20 Dec 2025 16:08:48 +0000",
    "thumbnail": "https://images.indianexpress.com/2025/12/stock-1-1.jpg",
    "importance": 35,
    "importanceLabel": "Medium",
    "updated_at": "2025-12-24T02:54:57.620380"
  },
  {
    "title": "Gold Climbs Above $4,500 for First Time on Geopolitics, Rates",
    "link": "https://www.bloomberg.com/news/articles/2025-12-23/gold-steadies-near-record-high-as-venezuela-tensions-persist",
    "source": "Bloomberg Markets",
    "category": "Markets & Finance",
    "published": "Tue, 23 Dec 2025 23:27:52 GMT",
    "thumbnail": "https://assets.bwbx.io/images/users/iqjWHBFdfxIU/iKPYBa_opCSI/v1/1200x-1.jpg",
    "importance": 30,
    "importanceLabel": "Medium",
    "updated_at": "2025-12-24T02:54:55.184384"
  },
  {
    "title": "Australian Dollar Climbs to Highest Since Oct. 2024 on RBA Bets",
    "link": "https://www.bloomberg.com/news/articles/2025-12-24/australian-dollar-climbs-to-highest-since-oct-2024-on-rba-bets",
    "source": "Bloomberg Markets",
    "category": "Markets & Finance",
    "published": "Wed, 24 Dec 2025 02:33:02 GMT",
    "thumbnail": "https://assets.bwbx.io/images/users/iqjWHBFdfxIU/iEtBxiC0vvJ0/v2/1200x-1.png",
    "importance": 30,
    "importanceLabel": "Medium",
    "updated_at": "2025-12-24T02:54:55.184418"
  },
  {
    "title": "Oil Holds Five-Day Gain With Geopolitics, Inventories in Focus",
    "link": "https://www.bloomberg.com/news/articles/2025-12-23/latest-oil-market-news-and-analysis-for-dec-24",
    "source": "Bloomberg Markets",
    "category": "Markets & Finance",
    "published": "Tue, 23 Dec 2025 23:27:03 GMT",
    "thumbnail": "https://assets.bwbx.io/images/users/iqjWHBFdfxIU/iLQm.5.eOv2k/v3/1200x-1.png",
    "importance": 30,
    "importanceLabel": "Medium",
    "updated_at": "2025-12-24T02:54:55.184523"
  },
  {
    "title": "General Atlantic, Kraft Group Bet $490 Million on Mexican Soccer Ahead of World Cup",
    "link": "https://www.bloomberg.com/news/articles/2025-12-24/us-investors-patriots-owner-bet-490-million-on-mexican-soccer-before-world-cup",
    "source": "Bloomberg Markets",
    "category": "Markets & Finance",
    "published": "Wed, 24 Dec 2025 01:05:30 GMT",
    "thumbnail": "https://assets.bwbx.io/images/users/iqjWHBFdfxIU/iqpQ8nu6ECrA/v1/1200x-1.jpg",
    "importance": 30,
    "importanceLabel": "Medium",
    "updated_at": "2025-12-24T02:54:55.184555"
  },
  {
    "title": "Platinum Soars to Record Above $2,300 on Tight Global Supplies",
    "link": "https://www.bloomberg.com/news/articles/2025-12-24/platinum-soars-to-record-above-2-300-on-tight-global-supplies",
    "source": "Bloomberg Markets",
    "category": "Markets & Finance",
    "published": "Wed, 24 Dec 2025 00:24:30 GMT",
    "thumbnail": "https://assets.bwbx.io/images/users/iqjWHBFdfxIU/i5NoB2QkpFPo/v3/1200x-1.png",
    "importance": 30,
    "importanceLabel": "Medium",
    "updated_at": "2025-12-24T02:54:55.184613"
  },
  {
    "title": "Decorated Army Veteran Builds Second Career in the Bourbon Business",
    "link": "https://www.bloomberg.com/news/videos/2025-12-23/army-veteran-builds-second-career-in-bourbon-business-video",
    "source": "Bloomberg Markets",
    "category": "Markets & Finance",
    "published": "Tue, 23 Dec 2025 23:49:36 GMT",
    "thumbnail": "https://assets.bwbx.io/images/users/iqjWHBFdfxIU/ivs44RNALch0/v3/1200x-1.jpg",
    "importance": 30,
    "importanceLabel": "Medium",
    "updated_at": "2025-12-24T02:54:55.184642"
  },
  {
    "title": "S&P 500 Hits Record High on Thin Volume | The Close 12/23/2025",
    "link": "https://www.bloomberg.com/news/videos/2025-12-23/the-close-12-23-2025-video",
    "source": "Bloomberg Markets",
    "category": "Markets & Finance",
    "published": "Tue, 23 Dec 2025 23:31:57 GMT",
    "thumbnail": "https://assets.bwbx.io/images/users/iqjWHBFdfxIU/iepBYjn6McNo/v3/1200x-1.jpg",
    "importance": 30,
    "importanceLabel": "Medium",
    "updated_at": "2025-12-24T02:54:55.184671"
  },
  {
    "title": "Tricolor CEO Collected $30 Million in Year Before Alleged Fraud",
    "link": "https://www.bloomberg.com/news/articles/2025-12-23/tricolor-ceo-collected-30-million-in-year-before-alleged-fraud",
    "source": "Bloomberg Markets",
    "category": "Markets & Finance",
    "published": "Tue, 23 Dec 2025 23:25:57 GMT",
    "thumbnail": "https://assets.bwbx.io/images/users/iqjWHBFdfxIU/iQmnWU5wQwZ8/v1/1200x-1.jpg",
    "importance": 30,
    "importanceLabel": "Medium",
    "updated_at": "2025-12-24T02:54:55.184699"
  },
  {
    "title": "Fashionphile CEO on Differentiating in Luxury Resale",
    "link": "https://www.bloomberg.com/news/videos/2025-12-23/fashionphile-ceo-on-differentiating-in-luxury-resale-video",
    "source": "Bloomberg Markets",
    "category": "Markets & Finance",
    "published": "Tue, 23 Dec 2025 23:02:13 GMT",
    "thumbnail": "https://assets.bwbx.io/images/users/iqjWHBFdfxIU/i6KsP.iH9GlU/v3/1200x-1.jpg",
    "importance": 30,
    "importanceLabel": "Medium",
    "updated_at": "2025-12-24T02:54:55.184751"
  },
  {
    "title": "Stew Leonard Jr. on Top Holiday Items, Viral Cookie Milk",
    "link": "https://www.bloomberg.com/news/videos/2025-12-23/stew-leonard-jr-on-top-holiday-items-viral-cookie-milk-video",
    "source": "Bloomberg Markets",
    "category": "Markets & Finance",
    "published": "Tue, 23 Dec 2025 22:54:04 GMT",
    "thumbnail": "https://assets.bwbx.io/images/users/iqjWHBFdfxIU/i_N.dJQ6DPII/v3/1200x-1.jpg",
    "importance": 30,
    "importanceLabel": "Medium",
    "updated_at": "2025-12-24T02:54:55.184820"
  },
  {
    "title": "Google-Backed Fleet Tracking Firm Motive Files Publicly for IPO",
    "link": "https://www.bloomberg.com/news/articles/2025-12-23/google-backed-fleet-tracking-firm-motive-files-publicly-for-ipo",
    "source": "Bloomberg Markets",
    "category": "Markets & Finance",
    "published": "Tue, 23 Dec 2025 22:51:01 GMT",
    "thumbnail": "https://assets.bwbx.io/images/users/iqjWHBFdfxIU/iij4a.hcaf98/v1/1200x-1.jpg",
    "importance": 30,
    "importanceLabel": "Medium",
    "updated_at": "2025-12-24T02:54:55.184850"
  },
  {
    "title": "US Airlines See Record Holiday Travel Even as Airfares Climb",
    "link": "https://www.bloomberg.com/news/videos/2025-12-23/airlines-see-record-holiday-travel-as-airfares-climb-video",
    "source": "Bloomberg Markets",
    "category": "Markets & Finance",
    "published": "Tue, 23 Dec 2025 22:44:48 GMT",
    "thumbnail": "https://assets.bwbx.io/images/users/iqjWHBFdfxIU/irWeIxLLtNHI/v3/1200x-1.jpg",
    "importance": 30,
    "importanceLabel": "Medium",
    "updated_at": "2025-12-24T02:54:55.184882"
  },
  {
    "title": "First Brands Trade Financier Seeks to Halt Its Use of Some Cash",
    "link": "https://www.bloomberg.com/news/articles/2025-12-23/first-brands-trade-financier-seeks-to-halt-its-use-of-some-cash",
    "source": "Bloomberg Markets",
    "category": "Markets & Finance",
    "published": "Tue, 23 Dec 2025 22:25:38 GMT",
    "thumbnail": "https://assets.bwbx.io/images/users/iqjWHBFdfxIU/iPWdmKvFAbD0/v1/1200x-1.jpg",
    "importance": 30,
    "importanceLabel": "Medium",
    "updated_at": "2025-12-24T02:54:55.184912"
  },
  {
    "title": "US economy grows at fastest pace in two years",
    "link": "https://www.bbc.com/news/articles/c62n9ynzrdpo?at_medium=RSS&at_campaign=rss",
    "source": "BBC News",
    "category": "Markets & Finance",
    "published": "Tue, 23 Dec 2025 15:56:57 GMT",
    "thumbnail": "https://ichef.bbci.co.uk/ace/standard/240/cpsprodpb/9d97/live/e58720c0-e002-11f0-ab61-73a5e79bafa0.jpg",
    "importance": 30,
    "importanceLabel": "Medium",
    "updated_at": "2025-12-24T02:54:55.942514"
  },
  {
    "title": "Government waters down inheritance tax plan for farms",
    "link": "https://www.bbc.com/news/articles/c8e9n3y28g1o?at_medium=RSS&at_campaign=rss",
    "source": "BBC News",
    "category": "Markets & Finance",
    "published": "Tue, 23 Dec 2025 17:29:09 GMT",
    "thumbnail": "https://ichef.bbci.co.uk/ace/standard/240/cpsprodpb/9a68/live/122654e0-dffc-11f0-a8dc-93c15fe68710.jpg",
    "importance": 30,
    "importanceLabel": "Medium",
    "updated_at": "2025-12-24T02:54:55.942541"
  },
  {
    "title": "US denies visas to ex-EU commissioner and others over social media rules",
    "link": "https://www.bbc.com/news/articles/cp39kngz008o?at_medium=RSS&at_campaign=rss",
    "source": "BBC News",
    "category": "Markets & Finance",
    "published": "Wed, 24 Dec 2025 00:45:28 GMT",
    "thumbnail": "https://ichef.bbci.co.uk/ace/standard/240/cpsprodpb/1292/live/5259b830-e05c-11f0-bdd6-e11ea3d501a5.jpg",
    "importance": 30,
    "importanceLabel": "Medium",
    "updated_at": "2025-12-24T02:54:55.942559"
  },
  {
    "title": "Rivalries and rumours: How the new order of the Murdoch dynasty is playing out",
    "link": "https://www.bbc.com/news/articles/clyd12d38jgo?at_medium=RSS&at_campaign=rss",
    "source": "BBC News",
    "category": "Markets & Finance",
    "published": "Wed, 24 Dec 2025 01:25:13 GMT",
    "thumbnail": "https://ichef.bbci.co.uk/ace/standard/240/cpsprodpb/bece/live/04dfd140-d9cf-11f0-a8dc-93c15fe68710.jpg",
    "importance": 30,
    "importanceLabel": "Medium",
    "updated_at": "2025-12-24T02:54:55.942577"
  },
  {
    "title": "Bet365 boss pay package rises to £280m",
    "link": "https://www.bbc.com/news/articles/c1j914rj64do?at_medium=RSS&at_campaign=rss",
    "source": "BBC News",
    "category": "Markets & Finance",
    "published": "Tue, 23 Dec 2025 11:39:05 GMT",
    "thumbnail": "https://ichef.bbci.co.uk/ace/standard/240/cpsprodpb/e156/live/3928c150-dff1-11f0-bc4a-ef4a2869974a.jpg",
    "importance": 30,
    "importanceLabel": "Medium",
    "updated_at": "2025-12-24T02:54:55.942592"
  },
  {
    "title": "The showers and baths keeping data centre tech cool",
    "link": "https://www.bbc.com/news/articles/cp8zd176516o?at_medium=RSS&at_campaign=rss",
    "source": "BBC News",
    "category": "Markets & Finance",
    "published": "Tue, 23 Dec 2025 00:04:45 GMT",
    "thumbnail": "https://ichef.bbci.co.uk/ace/standard/240/cpsprodpb/949d/live/c590f8c0-d032-11f0-9fb5-5f3a3703a365.jpg",
    "importance": 30,
    "importanceLabel": "Medium",
    "updated_at": "2025-12-24T02:54:55.942609"
  },
  {
    "title": "TikTok removes AI weight loss ads from fake Boots account",
    "link": "https://www.bbc.com/news/articles/c997lkdjdy5o?at_medium=RSS&at_campaign=rss",
    "source": "BBC News",
    "category": "Markets & Finance",
    "published": "Tue, 23 Dec 2025 09:23:51 GMT",
    "thumbnail": "https://ichef.bbci.co.uk/ace/standard/240/cpsprodpb/4611/live/67ea27b0-dd01-11f0-b67b-690eb873de1b.jpg",
    "importance": 30,
    "importanceLabel": "Medium",
    "updated_at": "2025-12-24T02:54:55.942625"
  },
  {
    "title": "Our son can't come home for Christmas after insulation mould took over",
    "link": "https://www.bbc.com/news/articles/cz0ne0k70dro?at_medium=RSS&at_campaign=rss",
    "source": "BBC News",
    "category": "Markets & Finance",
    "published": "Tue, 23 Dec 2025 07:44:32 GMT",
    "thumbnail": "https://ichef.bbci.co.uk/ace/standard/240/cpsprodpb/1172/live/b1e4ea90-dfcb-11f0-a8dc-93c15fe68710.jpg",
    "importance": 30,
    "importanceLabel": "Medium",
    "updated_at": "2025-12-24T02:54:55.942641"
  },
  {
    "title": "US regulator approves pill form of Wegovy weight-loss drug",
    "link": "https://www.bbc.com/news/articles/ce86le5dyxyo?at_medium=RSS&at_campaign=rss",
    "source": "BBC News",
    "category": "Markets & Finance",
    "published": "Tue, 23 Dec 2025 01:29:07 GMT",
    "thumbnail": "https://ichef.bbci.co.uk/ace/standard/240/cpsprodpb/8d12/live/22b79c30-dfd2-11f0-8f37-51273813293d.jpg",
    "importance": 30,
    "importanceLabel": "Medium",
    "updated_at": "2025-12-24T02:54:55.942690"
  },
  {
    "title": "Post Office had deal with Fujitsu to fix Horizon errors 19 years ago",
    "link": "https://www.bbc.com/news/articles/cqlkx6n15ero?at_medium=RSS&at_campaign=rss",
    "source": "BBC News",
    "category": "Markets & Finance",
    "published": "Mon, 22 Dec 2025 18:25:38 GMT",
    "thumbnail": "https://ichef.bbci.co.uk/ace/standard/240/cpsprodpb/0f8b/live/09562070-df5c-11f0-a8dc-93c15fe68710.jpg",
    "importance": 30,
    "importanceLabel": "Medium",
    "updated_at": "2025-12-24T02:54:55.942721"
  },
  {
    "title": "Lush co-founder takes pride in being a 'woke nerd'",
    "link": "https://www.bbc.com/news/articles/cjrj9529yn5o?at_medium=RSS&at_campaign=rss",
    "source": "BBC News",
    "category": "Markets & Finance",
    "published": "Mon, 22 Dec 2025 12:15:13 GMT",
    "thumbnail": "https://ichef.bbci.co.uk/ace/standard/240/cpsprodpb/a252/live/5e8e7980-dccc-11f0-bb5b-8b829d936cf4.jpg",
    "importance": 30,
    "importanceLabel": "Medium",
    "updated_at": "2025-12-24T02:54:55.942792"
  },
  {
    "title": "Petrol and diesel profit margins still persistently high, says watchdog",
    "link": "https://www.bbc.com/news/articles/c2dzk4kz722o?at_medium=RSS&at_campaign=rss",
    "source": "BBC News",
    "category": "Markets & Finance",
    "published": "Mon, 22 Dec 2025 14:29:52 GMT",
    "thumbnail": "https://ichef.bbci.co.uk/ace/standard/240/cpsprodpb/9a92/live/cb36e890-df26-11f0-9dac-b79514ec4a2d.jpg",
    "importance": 30,
    "importanceLabel": "Medium",
    "updated_at": "2025-12-24T02:54:55.942809"
  },
  {
    "title": "Gold and silver hit records as investors hunt for safety",
    "link": "https://www.bbc.com/news/articles/cd74ldr2zryo?at_medium=RSS&at_campaign=rss",
    "source": "BBC News",
    "category": "Markets & Finance",
    "published": "Mon, 22 Dec 2025 14:35:14 GMT",
    "thumbnail": "https://ichef.bbci.co.uk/ace/standard/240/cpsprodpb/299d/live/b4e710a0-df13-11f0-8db4-97f4d263443d.jpg",
    "importance": 30,
    "importanceLabel": "Medium",
    "updated_at": "2025-12-24T02:54:55.942825"
  },
  {
    "title": "Uber and Lyft announce plans to trial Chinese robotaxis in UK in 2026",
    "link": "https://www.bbc.com/news/articles/cy8jmx1dl9ro?at_medium=RSS&at_campaign=rss",
    "source": "BBC News",
    "category": "Markets & Finance",
    "published": "Mon, 22 Dec 2025 14:08:48 GMT",
    "thumbnail": "https://ichef.bbci.co.uk/ace/standard/240/cpsprodpb/7a81/live/5050e1a0-df24-11f0-9dac-b79514ec4a2d.jpg",
    "importance": 30,
    "importanceLabel": "Medium",
    "updated_at": "2025-12-24T02:54:55.942842"
  },
  {
    "title": "Why the railways often seem to be in such chaos over Christmas",
    "link": "https://www.bbc.com/news/articles/czdg795m5epo?at_medium=RSS&at_campaign=rss",
    "source": "BBC News",
    "category": "Markets & Finance",
    "published": "Mon, 22 Dec 2025 00:03:12 GMT",
    "thumbnail": "https://ichef.bbci.co.uk/ace/standard/240/cpsprodpb/ff22/live/8a4ad250-dc02-11f0-aae2-2191c0e48a3b.jpg",
    "importance": 30,
    "importanceLabel": "Medium",
    "updated_at": "2025-12-24T02:54:55.942859"
  },
  {
    "title": "Japan and US Agree to Expedite $550 Billion Investment Projects",
    "link": "https://www.bloomberg.com/news/articles/2025-12-24/japan-and-us-agree-to-expedite-550-billion-investment-projects",
    "source": "Bloomberg Economics",
    "category": "Global Economy",
    "published": "Wed, 24 Dec 2025 01:30:41 GMT",
    "thumbnail": "https://assets.bwbx.io/images/users/iqjWHBFdfxIU/i05pNYmfA2tA/v1/1200x-1.jpg",
    "importance": 30,
    "importanceLabel": "Medium",
    "updated_at": "2025-12-24T02:54:56.069229"
  },
  {
    "title": "South Korea’s Consumer Confidence Remains Positive for 8th Month",
    "link": "https://www.bloomberg.com/news/articles/2025-12-23/south-korea-s-consumer-confidence-remains-positive-for-8th-month",
    "source": "Bloomberg Economics",
    "category": "Global Economy",
    "published": "Tue, 23 Dec 2025 21:00:00 GMT",
    "thumbnail": "https://assets.bwbx.io/images/users/iqjWHBFdfxIU/ibpFp5vVP3Uw/v3/1200x-1.png",
    "importance": 30,
    "importanceLabel": "Medium",
    "updated_at": "2025-12-24T02:54:56.069262"
  },
  {
    "title": "Uruguay Cuts Key Rate to 7.5% With Inflation Below Target",
    "link": "https://www.bloomberg.com/news/articles/2025-12-23/uruguay-cuts-key-rate-to-7-5-with-inflation-below-target",
    "source": "Bloomberg Economics",
    "category": "Global Economy",
    "published": "Tue, 23 Dec 2025 20:31:08 GMT",
    "thumbnail": "https://assets.bwbx.io/images/users/iqjWHBFdfxIU/iMiC3_Qj_h9k/v1/1200x-1.jpg",
    "importance": 30,
    "importanceLabel": "Medium",
    "updated_at": "2025-12-24T02:54:56.069281"
  },
  {
    "title": "Argentines Pile Into Short-Term Bonds to Dodge FX Controls",
    "link": "https://www.bloomberg.com/news/articles/2025-12-23/argentines-pile-into-short-term-bonds-to-dodge-fx-controls",
    "source": "Bloomberg Economics",
    "category": "Global Economy",
    "published": "Tue, 23 Dec 2025 17:05:15 GMT",
    "thumbnail": "https://assets.bwbx.io/images/users/iqjWHBFdfxIU/iM5JwZchbvD8/v1/1200x-1.jpg",
    "importance": 30,
    "importanceLabel": "Medium",
    "updated_at": "2025-12-24T02:54:56.069356"
  },
  {
    "title": "Bessent Sees Room for a Future Revamp of the Fed’s 2% Target",
    "link": "https://www.bloomberg.com/news/articles/2025-12-23/bessent-sees-room-for-future-revamp-of-fed-2-inflation-target",
    "source": "Bloomberg Economics",
    "category": "Global Economy",
    "published": "Tue, 23 Dec 2025 15:27:19 GMT",
    "thumbnail": "https://assets.bwbx.io/images/users/iqjWHBFdfxIU/ijX1ex_3kuII/v1/1200x-1.jpg",
    "importance": 30,
    "importanceLabel": "Medium",
    "updated_at": "2025-12-24T02:54:56.069376"
  },
  {
    "title": "US Economy Grows at Fastest Pace in Years With 4.3% GDP Gain",
    "link": "https://www.bloomberg.com/news/articles/2025-12-23/us-economy-expanded-at-4-3-pace-fastest-in-two-years",
    "source": "Bloomberg Economics",
    "category": "Global Economy",
    "published": "Tue, 23 Dec 2025 13:33:11 GMT",
    "thumbnail": "https://assets.bwbx.io/images/users/iqjWHBFdfxIU/ijtheaURe3hg/v0/1200x-1.jpg",
    "importance": 30,
    "importanceLabel": "Medium",
    "updated_at": "2025-12-24T02:54:56.069410"
  },
  {
    "title": "Latin America’s Largest Economies See Annual Inflation Slowdown",
    "link": "https://www.bloomberg.com/news/articles/2025-12-23/brazil-inflation-edges-down-as-investors-mull-start-to-rate-cuts",
    "source": "Bloomberg Economics",
    "category": "Global Economy",
    "published": "Tue, 23 Dec 2025 12:07:33 GMT",
    "thumbnail": "https://assets.bwbx.io/images/users/iqjWHBFdfxIU/iwcgOfD7bYWI/v0/1200x-1.jpg",
    "importance": 30,
    "importanceLabel": "Medium",
    "updated_at": "2025-12-24T02:54:56.069467"
  },
  {
    "title": "Russia Moves to Legalize Domestic Crypto Deals for Retail Buyers",
    "link": "https://www.bloomberg.com/news/articles/2025-12-23/russia-moves-to-legalize-domestic-crypto-deals-for-retail-buyers",
    "source": "Bloomberg Economics",
    "category": "Global Economy",
    "published": "Tue, 23 Dec 2025 13:25:38 GMT",
    "thumbnail": "https://assets.bwbx.io/images/users/iqjWHBFdfxIU/islptmop34GI/v0/1200x-1.jpg",
    "importance": 30,
    "importanceLabel": "Medium",
    "updated_at": "2025-12-24T02:54:56.069504"
  },
  {
    "title": "Mexico Annual Inflation Slows, Backing Banxico Key Rate Cut",
    "link": "https://www.bloomberg.com/news/articles/2025-12-23/mexico-annual-inflation-slows-backing-banxico-s-key-rate-cut",
    "source": "Bloomberg Economics",
    "category": "Global Economy",
    "published": "Tue, 23 Dec 2025 12:19:24 GMT",
    "thumbnail": "https://assets.bwbx.io/images/users/iqjWHBFdfxIU/itZV_KWVLoXo/v1/1200x-1.jpg",
    "importance": 30,
    "importanceLabel": "Medium",
    "updated_at": "2025-12-24T02:54:56.069554"
  },
  {
    "title": "U.S. Inflation Slowed to 2.7% in November as Shutdown Distorts Data",
    "link": "https://www.nytimes.com/2025/12/18/business/economy/inflation-cpi-interest-rates.html",
    "source": "NYT > Business > Economy",
    "category": "Global Economy",
    "published": "Thu, 18 Dec 2025 16:20:00 +0000",
    "thumbnail": null,
    "importance": 30,
    "importanceLabel": "Medium",
    "updated_at": "2025-12-24T02:54:56.352972"
  },
  {
    "title": "The Fed Cut Rates Again but Deep Divisions Cloud Path Ahead",
    "link": "https://www.nytimes.com/2025/12/10/business/economy/fed-meeting-interest-rate-decision.html",
    "source": "NYT > Business > Economy",
    "category": "Global Economy",
    "published": "Wed, 10 Dec 2025 22:52:53 +0000",
    "thumbnail": null,
    "importance": 30,
    "importanceLabel": "Medium",
    "updated_at": "2025-12-24T02:54:56.353228"
  },
  {
    "title": "Powell Faces Pressure From Multiple Fronts as Fed Prepares to Cut Rates",
    "link": "https://www.nytimes.com/2025/12/08/business/economy/jerome-powell-federal-reserve.html",
    "source": "NYT > Business > Economy",
    "category": "Global Economy",
    "published": "Mon, 08 Dec 2025 10:03:07 +0000",
    "thumbnail": "https://static01.nyt.com/images/2025/12/08/multimedia/08dc-fed-qhbc/08dc-fed-qhbc-mediumSquareAt3X.jpg",
    "importance": 30,
    "importanceLabel": "Medium",
    "updated_at": "2025-12-24T02:54:56.353310"
  },
  {
    "title": "Ukraine Withdraws From Eastern Town, Complicating Negotiating Stance",
    "link": "https://www.nytimes.com/2025/12/23/world/europe/ukraine-russia-peace-plan-strikes.html",
    "source": "NYT > World News",
    "category": "Geopolitics",
    "published": "Tue, 23 Dec 2025 20:41:38 +0000",
    "thumbnail": "https://static01.nyt.com/images/2025/12/23/world/23ukraine-zelensky-sub-00001/23ukraine-zelensky-sub-00001-mediumSquareAt3X-v2.jpg",
    "importance": 30,
    "importanceLabel": "Medium",
    "updated_at": "2025-12-24T02:54:56.469238"
  },
  {
    "title": "Greta Thunberg Arrested at U.K. Protest Supporting Palestine Action Prisoners",
    "link": "https://www.nytimes.com/2025/12/23/world/europe/greta-thunberg-arrest-uk-palestine-action.html",
    "source": "NYT > World News",
    "category": "Geopolitics",
    "published": "Tue, 23 Dec 2025 16:12:50 +0000",
    "thumbnail": "https://static01.nyt.com/images/2025/12/23/world/23int-uk-thunberg-arrest-top-sub/23int-uk-thunberg-arrest-top-sub-mediumSquareAt3X.jpg",
    "importance": 30,
    "importanceLabel": "Medium",
    "updated_at": "2025-12-24T02:54:56.469318"
  },
  {
    "title": "After Bondi Massacre, a Moment of Unity. Then, Bitter Partisanship.",
    "link": "https://www.nytimes.com/2025/12/23/world/australia/australia-bondi-massacre-politics.html",
    "source": "NYT > World News",
    "category": "Geopolitics",
    "published": "Tue, 23 Dec 2025 21:07:28 +0000",
    "thumbnail": "https://static01.nyt.com/images/2025/12/23/multimedia/23int-oz-politics-01-qltz/23int-oz-politics-01-qltz-mediumSquareAt3X-v2.jpg",
    "importance": 30,
    "importanceLabel": "Medium",
    "updated_at": "2025-12-24T02:54:56.469358"
  },
  {
    "title": "The Strange Case of the Russian Snickers in U.K. Convenience Shops",
    "link": "https://www.nytimes.com/2025/12/23/world/europe/russian-snickers-candy-britain-trade.html",
    "source": "NYT > World News",
    "category": "Geopolitics",
    "published": "Tue, 23 Dec 2025 10:00:41 +0000",
    "thumbnail": "https://static01.nyt.com/images/2025/12/23/world/23int-UK-snickers/23int-UK-snickers-mediumSquareAt3X.jpg",
    "importance": 30,
    "importanceLabel": "Medium",
    "updated_at": "2025-12-24T02:54:56.469378"
  },
  {
    "title": "Christmas Is Back in Bethlehem, but Peace and Joy Have Yet to Arrive",
    "link": "https://www.nytimes.com/2025/12/22/world/middleeast/christmas-in-bethlehem-west-bank.html",
    "source": "NYT > World News",
    "category": "Geopolitics",
    "published": "Mon, 22 Dec 2025 17:16:05 +0000",
    "thumbnail": "https://static01.nyt.com/images/2025/12/16/world/00int-westbank-christmas-promo-1/00int-westbank-christmas-promo-1-mediumSquareAt3X.jpg",
    "importance": 30,
    "importanceLabel": "Medium",
    "updated_at": "2025-12-24T02:54:56.469513"
  },
  {
    "title": "China Delays Plans for Mass Production of Self-Driving Cars After Accident",
    "link": "https://www.nytimes.com/2025/12/23/business/china-autonomous-cars-driving.html",
    "source": "NYT > World News",
    "category": "Geopolitics",
    "published": "Tue, 23 Dec 2025 05:00:09 +0000",
    "thumbnail": "https://static01.nyt.com/images/2025/12/19/multimedia/00Biz-China-Autonomous-Cars-01-kmjg/00Biz-China-Autonomous-Cars-01-kmjg-mediumSquareAt3X.jpg",
    "importance": 30,
    "importanceLabel": "Medium",
    "updated_at": "2025-12-24T02:54:56.469621"
  },
  {
    "title": "Indian Navy’s Combat Aviation Capability Takes Wing",
    "link": "https://thediplomat.com/2025/12/indian-navys-combat-aviation-capability-takes-wing/",
    "source": "The Diplomat",
    "category": "Geopolitics",
    "published": "Tue, 23 Dec 2025 22:14:00 +0900",
    "thumbnail": "https://images.thediplomat.com/v1/td-list-l-2/2025/12/thediplomat_2025-12-23-221954.jpg",
    "importance": 30,
    "importanceLabel": "Medium",
    "updated_at": "2025-12-24T02:54:56.621098"
  },
  {
    "title": "China’s Quiet Stake in Post-Assad Syria",
    "link": "https://thediplomat.com/2025/12/chinas-quiet-stake-in-post-assad-syria/",
    "source": "The Diplomat",
    "category": "Geopolitics",
    "published": "Tue, 23 Dec 2025 22:15:00 +0900",
    "thumbnail": "https://images.thediplomat.com/v1/td-list-l-2/2024/12/thediplomat_2024-12-19-150411.jpg",
    "importance": 30,
    "importanceLabel": "Medium",
    "updated_at": "2025-12-24T02:54:56.621193"
  },
  {
    "title": "South Korea’s Labor Model and Its Strategic Consequences",
    "link": "https://thediplomat.com/2025/12/south-koreas-labor-model-and-its-strategic-consequences/",
    "source": "The Diplomat",
    "category": "Geopolitics",
    "published": "Tue, 23 Dec 2025 22:32:00 +0900",
    "thumbnail": "https://images.thediplomat.com/v1/td-list-l-2/2025/12/thediplomat_2025-12-23-223606.jpg",
    "importance": 30,
    "importanceLabel": "Medium",
    "updated_at": "2025-12-24T02:54:56.621234"
  },
  {
    "title": "What Gulirano Kosimova’s Case Reveals About Accountability in Uzbekistan",
    "link": "https://thediplomat.com/2025/12/what-gulirano-kosimovas-case-reveals-about-accountability-in-uzbekistan/",
    "source": "The Diplomat",
    "category": "Geopolitics",
    "published": "Tue, 23 Dec 2025 03:48:00 +0900",
    "thumbnail": "https://images.thediplomat.com/v1/td-list-l-2/2025/12/thediplomat_2025-12-23-035511.png",
    "importance": 30,
    "importanceLabel": "Medium",
    "updated_at": "2025-12-24T02:54:56.621401"
  },
  {
    "title": "China-US: A Rivalry Too Entangled to Decouple",
    "link": "https://thediplomat.com/2025/12/china-us-a-rivalry-too-entangled-to-decouple/",
    "source": "The Diplomat",
    "category": "Geopolitics",
    "published": "Tue, 23 Dec 2025 04:24:00 +0900",
    "thumbnail": "https://images.thediplomat.com/v1/td-list-l-2/2025/12/thediplomat_2025-12-23-042751.jpg",
    "importance": 30,
    "importanceLabel": "Medium",
    "updated_at": "2025-12-24T02:54:56.621443"
  },
  {
    "title": "How Would the Extradition of Sheikh Hasina from India to Bangladesh Work?",
    "link": "https://thediplomat.com/2025/12/how-would-the-extradition-of-sheikh-hasina-from-india-to-bangladesh-work/",
    "source": "The Diplomat",
    "category": "Geopolitics",
    "published": "Mon, 22 Dec 2025 21:36:00 +0900",
    "thumbnail": "https://images.thediplomat.com/v1/td-list-l-2/2025/11/thediplomat_2025-11-24-223358.jpg",
    "importance": 30,
    "importanceLabel": "Medium",
    "updated_at": "2025-12-24T02:54:56.621481"
  },
  {
    "title": "How Europe’s Preference for Plausible Deniability Shapes China’s Role in North Africa",
    "link": "https://thediplomat.com/2025/12/how-europes-preference-for-plausible-deniability-shapes-chinas-role-in-north-africa/",
    "source": "The Diplomat",
    "category": "Geopolitics",
    "published": "Mon, 22 Dec 2025 23:56:00 +0900",
    "thumbnail": "https://images.thediplomat.com/v1/td-list-l-2/2025/12/thediplomat_2025-12-22-235859.jpg",
    "importance": 30,
    "importanceLabel": "Medium",
    "updated_at": "2025-12-24T02:54:56.621505"
  },
  {
    "title": "‘We’re the biggest fugitives’: Lalit Modi, Vijay Mallya taunt India with a message from London",
    "link": "https://indianexpress.com/article/world/lalit-modi-vijay-mallya-video-from-london-biggest-fugitives-10435672/",
    "source": "World | The Indian Express",
    "category": "Geopolitics",
    "published": "Tue, 23 Dec 2025 19:06:41 +0000",
    "thumbnail": "https://images.indianexpress.com/2025/12/lalit-modi.jpg",
    "importance": 30,
    "importanceLabel": "Medium",
    "updated_at": "2025-12-24T02:54:57.045901"
  },
  {
    "title": "PM Karki, ex-PMs Oli, Dueba, ‘Prachanda’ vow to create conducive election environment",
    "link": "https://indianexpress.com/article/world/pm-karki-ex-pm-oli-dueba-prachanda-create-conducive-election-environment-10435595/",
    "source": "World | The Indian Express",
    "category": "Geopolitics",
    "published": "Tue, 23 Dec 2025 17:21:51 +0000",
    "thumbnail": "https://images.indianexpress.com/2025/09/Sushila-Karki-1.jpg",
    "importance": 30,
    "importanceLabel": "Medium",
    "updated_at": "2025-12-24T02:54:57.045973"
  },
  {
    "title": "Louvre tightens security after $102 million jewel heist, installs bars on infamous window",
    "link": "https://indianexpress.com/article/world/louvre-tightens-security-102-million-jewel-heist-installs-bars-infamous-window-10435581/",
    "source": "World | The Indian Express",
    "category": "Geopolitics",
    "published": "Tue, 23 Dec 2025 17:13:48 +0000",
    "thumbnail": "https://images.indianexpress.com/2025/12/louvre.jpg",
    "importance": 30,
    "importanceLabel": "Medium",
    "updated_at": "2025-12-24T02:54:57.045993"
  },
  {
    "title": "Why New Zealand Foreign Minister slammed trade agreement with India: ‘Bad deal’",
    "link": "https://indianexpress.com/article/world/new-zealand-foreign-minister-slams-india-trade-agreement-fta-immigration-10434978/",
    "source": "World | The Indian Express",
    "category": "Geopolitics",
    "published": "Tue, 23 Dec 2025 12:56:56 +0000",
    "thumbnail": "https://images.indianexpress.com/2025/12/winston-peters.png",
    "importance": 30,
    "importanceLabel": "Medium",
    "updated_at": "2025-12-24T02:54:57.046160"
  },
  {
    "title": "Bangladesh summons Indian High Commissioner Pranay Verma, expresses ‘deep concern over violent protests’ outside missions",
    "link": "https://indianexpress.com/article/world/bangladesh-summons-indian-high-commissioner-pranay-verma-expresses-deep-concern-over-violent-protests-outside-missions-10434642/",
    "source": "World | The Indian Express",
    "category": "Geopolitics",
    "published": "Tue, 23 Dec 2025 08:40:20 +0000",
    "thumbnail": "https://images.indianexpress.com/2025/12/India-Bangladesh_20251223052945.jpg",
    "importance": 30,
    "importanceLabel": "Medium",
    "updated_at": "2025-12-24T02:54:57.046250"
  },
  {
    "title": "What is Trump’s ‘Golden Fleet’? US president outlines plan for new Navy battleship",
    "link": "https://indianexpress.com/article/world/what-is-trumps-golden-fleet-us-president-outlines-plan-for-new-navy-battleship-10434173/",
    "source": "World | The Indian Express",
    "category": "Geopolitics",
    "published": "Tue, 23 Dec 2025 05:41:06 +0000",
    "thumbnail": "https://images.indianexpress.com/2025/12/US-3-24.jpg",
    "importance": 30,
    "importanceLabel": "Medium",
    "updated_at": "2025-12-24T02:54:57.046271"
  },
  {
    "title": "Indian investors ramp up overseas bets as US markets outperform",
    "link": "https://indianexpress.com/article/business/indian-investors-overseas-bets-us-markets-outperform-10435519/",
    "source": "Business | The Indian Express",
    "category": "Business",
    "published": "Tue, 23 Dec 2025 16:30:15 +0000",
    "thumbnail": "https://images.indianexpress.com/2025/09/BSE-1.jpg",
    "importance": 30,
    "importanceLabel": "Medium",
    "updated_at": "2025-12-24T02:54:57.620033"
  },
  {
    "title": "Net FDI outflow again in Oct; foreign repatriations, Indian firms’ overseas investment above $8 billion",
    "link": "https://indianexpress.com/article/business/net-fdi-outflow-again-in-oct-foreign-repatriations-indian-firms-overseas-investment-above-8-billion-10433593/",
    "source": "Business | The Indian Express",
    "category": "Business",
    "published": "Mon, 22 Dec 2025 16:20:37 +0000",
    "thumbnail": "https://images.indianexpress.com/2025/12/fdi.jpg",
    "importance": 30,
    "importanceLabel": "Medium",
    "updated_at": "2025-12-24T02:54:57.620220"
  },
  {
    "title": "‘MUFG deal a huge endorsement of India’s progress’: Shriram Finance",
    "link": "https://indianexpress.com/article/business/mufg-deal-a-huge-endorsement-of-indias-progress-shriram-finance-10433479/",
    "source": "Business | The Indian Express",
    "category": "Business",
    "published": "Mon, 22 Dec 2025 14:24:39 +0000",
    "thumbnail": "https://images.indianexpress.com/2025/12/shriram.jpg",
    "importance": 30,
    "importanceLabel": "Medium",
    "updated_at": "2025-12-24T02:54:57.620241"
  },
  {
    "title": "Bank of Canada Uncertain If Next Rate Move Will Be Cut or Hike",
    "link": "https://www.bloomberg.com/news/articles/2025-12-23/bank-of-canada-uncertain-if-next-rate-move-will-be-cut-or-hike",
    "source": "Bloomberg Economics",
    "category": "Global Economy",
    "published": "Tue, 23 Dec 2025 18:30:00 GMT",
    "thumbnail": "https://assets.bwbx.io/images/users/iqjWHBFdfxIU/iLxLAHRrG5Os/v1/1200x-1.jpg",
    "importance": 25,
    "importanceLabel": "Low",
    "updated_at": "2025-12-24T02:54:56.069300"
  },
  {
    "title": "Canada Economy Grew Slightly in November Following October Dip",
    "link": "https://www.bloomberg.com/news/articles/2025-12-23/canada-economy-grew-in-november-following-october-dip",
    "source": "Bloomberg Economics",
    "category": "Global Economy",
    "published": "Tue, 23 Dec 2025 13:36:20 GMT",
    "thumbnail": "https://assets.bwbx.io/images/users/iqjWHBFdfxIU/iig20SE0oucU/v0/1200x-1.jpg",
    "importance": 25,
    "importanceLabel": "Low",
    "updated_at": "2025-12-24T02:54:56.069318"
  },
  {
    "title": "Starmer Retreats on Inheritance Tax After Farmers’ Backlash",
    "link": "https://www.bloomberg.com/news/articles/2025-12-23/uk-backs-down-to-farmers-by-lifting-inheritance-tax-threshold",
    "source": "Bloomberg Economics",
    "category": "Global Economy",
    "published": "Tue, 23 Dec 2025 12:04:02 GMT",
    "thumbnail": "https://assets.bwbx.io/images/users/iqjWHBFdfxIU/iTlRprtxiZmc/v0/1200x-1.jpg",
    "importance": 25,
    "importanceLabel": "Low",
    "updated_at": "2025-12-24T02:54:56.069339"
  },
  {
    "title": "Turkey Raises Minimum Wage by 27%, in Line With Expectations",
    "link": "https://www.bloomberg.com/news/articles/2025-12-23/turkey-raises-minimum-wage-by-27-in-line-with-expectations",
    "source": "Bloomberg Economics",
    "category": "Global Economy",
    "published": "Tue, 23 Dec 2025 15:54:00 GMT",
    "thumbnail": "https://assets.bwbx.io/images/users/iqjWHBFdfxIU/iKbwx6DkYcB0/v0/1200x-1.jpg",
    "importance": 25,
    "importanceLabel": "Low",
    "updated_at": "2025-12-24T02:54:56.069393"
  },
  {
    "title": "US Consumer Confidence Drops for Fifth Straight Month",
    "link": "https://www.bloomberg.com/news/articles/2025-12-23/us-consumer-confidence-drops-for-fifth-straight-month",
    "source": "Bloomberg Economics",
    "category": "Global Economy",
    "published": "Tue, 23 Dec 2025 15:03:30 GMT",
    "thumbnail": "https://assets.bwbx.io/images/users/iqjWHBFdfxIU/iqyEi9lirMLQ/v1/1200x-1.jpg",
    "importance": 25,
    "importanceLabel": "Low",
    "updated_at": "2025-12-24T02:54:56.069425"
  },
  {
    "title": "Why a Weak Japanese Yen Could Trigger Government Intervention",
    "link": "https://www.bloomberg.com/news/articles/2025-12-23/japan-why-is-the-yen-so-weak-how-would-the-boj-intervene-jpy-usd",
    "source": "Bloomberg Economics",
    "category": "Global Economy",
    "published": "Tue, 23 Dec 2025 13:12:50 GMT",
    "thumbnail": "https://assets.bwbx.io/images/users/iqjWHBFdfxIU/iFzVQZoTRsNY/v0/1200x-1.jpg",
    "importance": 25,
    "importanceLabel": "Low",
    "updated_at": "2025-12-24T02:54:56.069521"
  },
  {
    "title": "Poland Seeks G-20 Membership to Give Voice to Eastern Europe",
    "link": "https://www.bloomberg.com/news/articles/2025-12-23/poland-seeks-g-20-membership-to-give-voice-to-eastern-europe",
    "source": "Bloomberg Economics",
    "category": "Global Economy",
    "published": "Tue, 23 Dec 2025 13:07:37 GMT",
    "thumbnail": "https://assets.bwbx.io/images/users/iqjWHBFdfxIU/isN_jeRfE.lM/v0/1200x-1.jpg",
    "importance": 25,
    "importanceLabel": "Low",
    "updated_at": "2025-12-24T02:54:56.069538"
  },
  {
    "title": "How Walmart Finds Success Hiring Truckers Amid Driver Shortage",
    "link": "https://www.bloomberg.com/news/newsletters/2025-12-23/how-walmart-finds-success-hiring-truckers-amid-driver-shortage",
    "source": "Bloomberg Economics",
    "category": "Global Economy",
    "published": "Tue, 23 Dec 2025 12:00:01 GMT",
    "thumbnail": "https://assets.bwbx.io/images/users/iqjWHBFdfxIU/i3s_yzFPoE0I/v8/1200x-1.jpg",
    "importance": 25,
    "importanceLabel": "Low",
    "updated_at": "2025-12-24T02:54:56.069572"
  },
  {
    "title": "Goldman Sees New Year US Growth Boom, But Citigroup Is Skeptical",
    "link": "https://www.bloomberg.com/news/newsletters/2025-12-23/goldman-sachs-and-citigroup-diverge-in-forecasts-for-us-2026-economic-growth",
    "source": "Bloomberg Economics",
    "category": "Global Economy",
    "published": "Tue, 23 Dec 2025 12:00:01 GMT",
    "thumbnail": "https://assets.bwbx.io/images/users/iqjWHBFdfxIU/iN65L1cj8EQo/v7/1200x-1.jpg",
    "importance": 25,
    "importanceLabel": "Low",
    "updated_at": "2025-12-24T02:54:56.069589"
  },
  {
    "title": "U.S. Coast Guard Pursues Oil Tanker Linked to Venezuela",
    "link": "https://www.nytimes.com/2025/12/21/us/politics/us-coast-guard-venezuela-oil-tankers.html",
    "source": "NYT > Business > Economy",
    "category": "Global Economy",
    "published": "Mon, 22 Dec 2025 04:58:03 +0000",
    "thumbnail": "https://static01.nyt.com/images/2025/12/21/multimedia/21dc-tanker-update-ww/21dc-tanker-hp-glzt-mediumSquareAt3X.jpg",
    "importance": 25,
    "importanceLabel": "Low",
    "updated_at": "2025-12-24T02:54:56.352885"
  },
  {
    "title": "Why Middle-Class Americans Say Life Is Unaffordable",
    "link": "https://www.nytimes.com/2025/12/20/us/politics/middle-class-us-economy-affordability.html",
    "source": "NYT > Business > Economy",
    "category": "Global Economy",
    "published": "Sat, 20 Dec 2025 10:00:55 +0000",
    "thumbnail": "https://static01.nyt.com/images/2025/12/20/multimedia/20nat-affordability-vtbz/20nat-affordability-vtbz-mediumSquareAt3X.jpg",
    "importance": 25,
    "importanceLabel": "Low",
    "updated_at": "2025-12-24T02:54:56.352912"
  },
  {
    "title": "‘A Singularly Turbulent Time’: Deeper Uncertainty in Store for Global Economy",
    "link": "https://www.nytimes.com/2025/12/19/business/economy/trump-trade-global-econ.html",
    "source": "NYT > Business > Economy",
    "category": "Global Economy",
    "published": "Fri, 19 Dec 2025 18:55:41 +0000",
    "thumbnail": "https://static01.nyt.com/images/2025/12/19/espanol/19Biz-Global-Econ-01-khcw-ES-copy1/19Biz-Global-Econ-01-khcw-mediumSquareAt3X.jpg",
    "importance": 25,
    "importanceLabel": "Low",
    "updated_at": "2025-12-24T02:54:56.352939"
  },
  {
    "title": "Trump Dangles Cash Payments to Assuage Affordability Concerns",
    "link": "https://www.nytimes.com/2025/12/17/us/politics/trump-cash-payments.html",
    "source": "NYT > Business > Economy",
    "category": "Global Economy",
    "published": "Wed, 17 Dec 2025 13:56:50 +0000",
    "thumbnail": "https://static01.nyt.com/images/2025/12/17/multimedia/17dc-trump-cash-gvhq/17dc-trump-cash-gvhq-mediumSquareAt3X.jpg",
    "importance": 25,
    "importanceLabel": "Low",
    "updated_at": "2025-12-24T02:54:56.352992"
  },
  {
    "title": "U.S. Threatens Penalties Against European Tech Firms Amid Regulatory Fight",
    "link": "https://www.nytimes.com/2025/12/16/business/economy/us-eu-tech-penalties.html",
    "source": "NYT > Business > Economy",
    "category": "Global Economy",
    "published": "Wed, 17 Dec 2025 00:23:46 +0000",
    "thumbnail": "https://static01.nyt.com/images/2025/12/16/multimedia/16dc-eu-us-trade-tjgw/16dc-eu-us-trade-tjgw-mediumSquareAt3X.jpg",
    "importance": 25,
    "importanceLabel": "Low",
    "updated_at": "2025-12-24T02:54:56.353013"
  },
  {
    "title": "White House Dismisses Rise in Unemployment",
    "link": "https://www.nytimes.com/2025/12/16/us/politics/trump-administration-unemployment-rate-economy.html",
    "source": "NYT > Business > Economy",
    "category": "Global Economy",
    "published": "Tue, 16 Dec 2025 20:33:08 +0000",
    "thumbnail": "https://static01.nyt.com/images/2025/12/17/multimedia/17dc-trump-jobs-lhqm/17dc-trump-jobs-lhqm-mediumSquareAt3X.jpg",
    "importance": 25,
    "importanceLabel": "Low",
    "updated_at": "2025-12-24T02:54:56.353030"
  },
  {
    "title": "Europe May Roll Back Combustion Engine Ban",
    "link": "https://www.nytimes.com/2025/12/16/business/economy/europe-auto-emissions-ban.html",
    "source": "NYT > Business > Economy",
    "category": "Global Economy",
    "published": "Tue, 16 Dec 2025 19:00:16 +0000",
    "thumbnail": "https://static01.nyt.com/images/2025/12/16/multimedia/16Biz-Eu-Emissions-pqlm/16Biz-Eu-Emissions-pqlm-mediumSquareAt3X.jpg",
    "importance": 25,
    "importanceLabel": "Low",
    "updated_at": "2025-12-24T02:54:56.353047"
  },
  {
    "title": "Jobs Report Could Provide Overdue Clarity on Uncertain Economy",
    "link": "https://www.nytimes.com/2025/12/16/business/economy/jobs-report-unemployment-november.html",
    "source": "NYT > Business > Economy",
    "category": "Global Economy",
    "published": "Tue, 16 Dec 2025 20:26:21 +0000",
    "thumbnail": null,
    "importance": 25,
    "importanceLabel": "Low",
    "updated_at": "2025-12-24T02:54:56.353075"
  },
  {
    "title": "U.S.-U.K. Trade Deal Hits Stumbling Block",
    "link": "https://www.nytimes.com/2025/12/13/business/economy/trump-uk-trade-deal-tariffs.html",
    "source": "NYT > Business > Economy",
    "category": "Global Economy",
    "published": "Sat, 13 Dec 2025 17:48:08 +0000",
    "thumbnail": "https://static01.nyt.com/images/2025/12/13/multimedia/13biz-uk-us-trade-pvkf/13biz-uk-us-trade-pvkf-mediumSquareAt3X.jpg",
    "importance": 25,
    "importanceLabel": "Low",
    "updated_at": "2025-12-24T02:54:56.353093"
  },
  {
    "title": "Trump’s $100,000 H-1B Fee Faces Lawsuit",
    "link": "https://www.nytimes.com/2025/12/13/us/politics/states-lawsuit-h1b-visas.html",
    "source": "NYT > Business > Economy",
    "category": "Global Economy",
    "published": "Sat, 13 Dec 2025 06:26:16 +0000",
    "thumbnail": "https://static01.nyt.com/images/2025/09/20/multimedia/12trump-news-h1b-suit/20biz-h1b-visas-lfcz-mediumSquareAt3X-v2.jpg",
    "importance": 25,
    "importanceLabel": "Low",
    "updated_at": "2025-12-24T02:54:56.353113"
  },
  {
    "title": "Businesses Are Cashing In on Trump’s Tax Cuts",
    "link": "https://www.nytimes.com/2025/12/12/us/politics/trumps-corporate-tax-cuts-economy.html",
    "source": "NYT > Business > Economy",
    "category": "Global Economy",
    "published": "Fri, 12 Dec 2025 17:08:35 +0000",
    "thumbnail": "https://static01.nyt.com/images/2025/12/12/multimedia/12dc-taxcuts-qpcj/12dc-taxcuts-qpcj-mediumSquareAt3X-v2.jpg",
    "importance": 25,
    "importanceLabel": "Low",
    "updated_at": "2025-12-24T02:54:56.353135"
  },
  {
    "title": "Trump’s Tariffs Shrank the U.S. Trade Deficit in September",
    "link": "https://www.nytimes.com/2025/12/11/business/economy/trump-tariffs-trade-deficit.html",
    "source": "NYT > Business > Economy",
    "category": "Global Economy",
    "published": "Thu, 11 Dec 2025 17:06:12 +0000",
    "thumbnail": "https://static01.nyt.com/images/2025/12/10/multimedia/2025-biz-standalone-promos-new-2025-12-11-monthy-trade/2025-biz-standalone-promos-new-2025-12-11-monthy-trade-mediumSquareAt3X-v12.png",
    "importance": 25,
    "importanceLabel": "Low",
    "updated_at": "2025-12-24T02:54:56.353178"
  },
  {
    "title": "Trump Doesn’t Want to Talk About Affordability. Democrats Say That’s a Gift.",
    "link": "https://www.nytimes.com/2025/12/11/us/politics/trump-affordability-democrats.html",
    "source": "NYT > Business > Economy",
    "category": "Global Economy",
    "published": "Thu, 11 Dec 2025 14:24:28 +0000",
    "thumbnail": "https://static01.nyt.com/images/2025/12/10/multimedia/10DC-ASSESS-hfzk/10DC-ASSESS-hfzk-mediumSquareAt3X.jpg",
    "importance": 25,
    "importanceLabel": "Low",
    "updated_at": "2025-12-24T02:54:56.353201"
  },
  {
    "title": "Trump’s Nvidia Chip Deal Reverses Decades of Technology Restrictions",
    "link": "https://www.nytimes.com/2025/12/09/us/politics/trump-nvidia-ai-chips-china.html",
    "source": "NYT > Business > Economy",
    "category": "Global Economy",
    "published": "Mon, 15 Dec 2025 19:05:22 +0000",
    "thumbnail": "https://static01.nyt.com/images/2025/12/09/multimedia/09dc-chips-assess-mbjl/09dc-chips-assess-mbjl-mediumSquareAt3X.jpg",
    "importance": 25,
    "importanceLabel": "Low",
    "updated_at": "2025-12-24T02:54:56.353252"
  },
  {
    "title": "Why the A.I. Boom Is Unlike the Dot-Com Boom",
    "link": "https://www.nytimes.com/2025/12/09/technology/ai-boom-unlike-dot-com-boom.html",
    "source": "NYT > Business > Economy",
    "category": "Global Economy",
    "published": "Tue, 09 Dec 2025 16:31:38 +0000",
    "thumbnail": "https://static01.nyt.com/images/2025/12/08/business/00biz-dotcom-Ben/00biz-dotcom-Ben-mediumSquareAt3X.jpg",
    "importance": 25,
    "importanceLabel": "Low",
    "updated_at": "2025-12-24T02:54:56.353272"
  },
  {
    "title": "Trump Defends Tariffs Amid Growing Concerns Over Affordability",
    "link": "https://www.nytimes.com/2025/12/08/us/politics/trump-trade-affordability.html",
    "source": "NYT > Business > Economy",
    "category": "Global Economy",
    "published": "Wed, 10 Dec 2025 08:00:11 +0000",
    "thumbnail": "https://static01.nyt.com/images/2025/12/08/multimedia/08DC-TRUMP-ASSESS-zbwq/08DC-TRUMP-ASSESS-zbwq-mediumSquareAt3X-v2.jpg",
    "importance": 25,
    "importanceLabel": "Low",
    "updated_at": "2025-12-24T02:54:56.353291"
  },
  {
    "title": "France Fails to Adopt a Budget by Year’s End. Again.",
    "link": "https://www.nytimes.com/2025/12/23/world/europe/france-budget-special-law.html",
    "source": "NYT > World News",
    "category": "Geopolitics",
    "published": "Tue, 23 Dec 2025 21:00:20 +0000",
    "thumbnail": "https://static01.nyt.com/images/2025/12/23/multimedia/23int-france-budget-01-bfql/23int-france-budget-01-bfql-mediumSquareAt3X.jpg",
    "importance": 25,
    "importanceLabel": "Low",
    "updated_at": "2025-12-24T02:54:56.469296"
  },
  {
    "title": "Italian Artisans Add Figurines of Donald Trump to Nativity Scenes",
    "link": "https://www.nytimes.com/2025/12/23/world/europe/naples-trump-figurines-nativity-christmas.html",
    "source": "NYT > World News",
    "category": "Geopolitics",
    "published": "Tue, 23 Dec 2025 10:17:10 +0000",
    "thumbnail": "https://static01.nyt.com/images/2025/12/23/multimedia/23int-italy-christmas-01-kclb/23int-italy-christmas-01-kclb-mediumSquareAt3X.jpg",
    "importance": 25,
    "importanceLabel": "Low",
    "updated_at": "2025-12-24T02:54:56.469338"
  },
  {
    "title": "German Leaders, Undercutting the Far Right, Are Leaning on the Far Left",
    "link": "https://www.nytimes.com/2025/12/23/world/europe/germany-parliament-die-linke.html",
    "source": "NYT > World News",
    "category": "Geopolitics",
    "published": "Tue, 23 Dec 2025 10:00:07 +0000",
    "thumbnail": "https://static01.nyt.com/images/2025/12/23/multimedia/23int-germany-left-01-wlvt/23int-germany-left-01-wlvt-mediumSquareAt3X.jpg",
    "importance": 25,
    "importanceLabel": "Low",
    "updated_at": "2025-12-24T02:54:56.469398"
  },
  {
    "title": "Trump Tariffs Threaten Canadian Holiday Sales",
    "link": "https://www.nytimes.com/2025/12/23/world/canada/canada-trump-tariffs-christmas.html",
    "source": "NYT > World News",
    "category": "Geopolitics",
    "published": "Tue, 23 Dec 2025 10:00:35 +0000",
    "thumbnail": "https://static01.nyt.com/images/2025/12/23/multimedia/23int-Canada-christmas-tariff-tbcm/23int-Canada-christmas-tariff-tbcm-mediumSquareAt3X.jpg",
    "importance": 25,
    "importanceLabel": "Low",
    "updated_at": "2025-12-24T02:54:56.469417"
  },
  {
    "title": "After the Assad Regime’s Fall, His Enforcers Are Lying Low and Living Large",
    "link": "https://www.nytimes.com/2025/12/22/world/middleeast/assad-syria-enforcers-lives-now.html",
    "source": "NYT > World News",
    "category": "Geopolitics",
    "published": "Mon, 22 Dec 2025 17:40:24 +0000",
    "thumbnail": null,
    "importance": 25,
    "importanceLabel": "Low",
    "updated_at": "2025-12-24T02:54:56.469453"
  },
  {
    "title": "As Trump Clings to Tariffs, His Argentine Ally Is Opening Up to Trade",
    "link": "https://www.nytimes.com/2025/12/22/world/americas/argentina-trade.html",
    "source": "NYT > World News",
    "category": "Geopolitics",
    "published": "Mon, 22 Dec 2025 12:59:57 +0000",
    "thumbnail": "https://static01.nyt.com/images/2025/12/22/multimedia/22int-argentina-consumption-promo/22int-argentina-consumption-jczq-mediumSquareAt3X.jpg",
    "importance": 25,
    "importanceLabel": "Low",
    "updated_at": "2025-12-24T02:54:56.469475"
  },
  {
    "title": "What We Know About U.S. Interceptions of Oil Tankers in Venezuela",
    "link": "https://www.nytimes.com/2025/12/22/us/politics/trump-oil-tankers-venezuela.html",
    "source": "NYT > World News",
    "category": "Geopolitics",
    "published": "Mon, 22 Dec 2025 18:07:21 +0000",
    "thumbnail": "https://static01.nyt.com/images/2025/12/22/multimedia/22dc-tankers-WWK-vqcp/22dc-tankers-WWK-vqcp-mediumSquareAt3X.jpg",
    "importance": 25,
    "importanceLabel": "Low",
    "updated_at": "2025-12-24T02:54:56.469494"
  },
  {
    "title": "Lynching of a Hindu in Bangladesh Fans Fears of Rising Intolerance",
    "link": "https://www.nytimes.com/2025/12/22/world/asia/bangladesh-hindu-muslim-lynching.html",
    "source": "NYT > World News",
    "category": "Geopolitics",
    "published": "Mon, 22 Dec 2025 22:15:56 +0000",
    "thumbnail": "https://static01.nyt.com/images/2025/12/22/multimedia/22int-bangladesh-lynching-tphf/22int-bangladesh-lynching-tphf-mediumSquareAt3X.jpg",
    "importance": 25,
    "importanceLabel": "Low",
    "updated_at": "2025-12-24T02:54:56.469537"
  },
  {
    "title": "Trump’s Tanker Crackdown Paralyzes Venezuelan Oil Exports",
    "link": "https://www.nytimes.com/2025/12/23/world/americas/trump-tankers-venezuela-oil-industry.html",
    "source": "NYT > World News",
    "category": "Geopolitics",
    "published": "Tue, 23 Dec 2025 23:00:23 +0000",
    "thumbnail": "https://static01.nyt.com/images/2025/12/23/multimedia/23int-venezuela-oil-bgcw/23int-venezuela-oil-bgcw-mediumSquareAt3X.jpg",
    "importance": 25,
    "importanceLabel": "Low",
    "updated_at": "2025-12-24T02:54:56.469560"
  },
  {
    "title": "Dating ChatGPT",
    "link": "https://www.nytimes.com/2025/12/23/world/dating-chatgpt-greta-thunberg-russia-ukraine.html",
    "source": "NYT > World News",
    "category": "Geopolitics",
    "published": "Tue, 23 Dec 2025 21:17:14 +0000",
    "thumbnail": "https://static01.nyt.com/images/2025/12/24/pageoneplus/24int-theworld-lede/24int-theworld-lede-mediumSquareAt3X-v2.png",
    "importance": 25,
    "importanceLabel": "Low",
    "updated_at": "2025-12-24T02:54:56.469601"
  },
  {
    "title": "Trump Administration Orders Nearly 30 U.S. Ambassadors to Leave Their Posts",
    "link": "https://www.nytimes.com/2025/12/22/us/politics/trump-administration-ambassadors-posts.html",
    "source": "NYT > World News",
    "category": "Geopolitics",
    "published": "Tue, 23 Dec 2025 03:40:21 +0000",
    "thumbnail": "https://static01.nyt.com/images/2025/12/22/multimedia/22dc-diplo-qfgp/22dc-diplo-qfgp-mediumSquareAt3X.jpg",
    "importance": 25,
    "importanceLabel": "Low",
    "updated_at": "2025-12-24T02:54:56.469642"
  },
  {
    "title": "Trump Administration Oil Tanker Seizures Are Meant to Force Maduro Out, Officials Say",
    "link": "https://www.nytimes.com/2025/12/22/world/americas/trump-venezuela-oil-tankers-maduro.html",
    "source": "NYT > World News",
    "category": "Geopolitics",
    "published": "Tue, 23 Dec 2025 04:12:46 +0000",
    "thumbnail": "https://static01.nyt.com/images/2025/12/22/multimedia/22int-tankers-us-venezula-jhzk/22int-tankers-us-venezula-jhzk-mediumSquareAt3X.jpg",
    "importance": 25,
    "importanceLabel": "Low",
    "updated_at": "2025-12-24T02:54:56.469662"
  },
  {
    "title": "Killing of Tajik Boy in Moscow Sparks Debate About Motive",
    "link": "https://thediplomat.com/2025/12/killing-of-tajik-boy-in-moscow-sparks-debate-about-motive/",
    "source": "The Diplomat",
    "category": "Geopolitics",
    "published": "Tue, 23 Dec 2025 23:21:00 +0900",
    "thumbnail": "https://images.thediplomat.com/v1/td-list-l-2/2025/12/thediplomat_2025-12-23-232600.jpg",
    "importance": 25,
    "importanceLabel": "Low",
    "updated_at": "2025-12-24T02:54:56.621127"
  },
  {
    "title": "Malaysian Court Rejects Former PM Najib’s House Arrest Bid",
    "link": "https://thediplomat.com/2025/12/malaysian-court-rejects-former-pm-najibs-house-arrest-bid/",
    "source": "The Diplomat",
    "category": "Geopolitics",
    "published": "Tue, 23 Dec 2025 09:01:00 +0900",
    "thumbnail": "https://images.thediplomat.com/v1/td-list-l-2/2025/12/thediplomat_2025-12-23-090752.jpg",
    "importance": 25,
    "importanceLabel": "Low",
    "updated_at": "2025-12-24T02:54:56.621172"
  },
  {
    "title": "Why is Türkiye Interested in South Asia?",
    "link": "https://thediplomat.com/2025/12/why-is-turkiye-interested-in-south-asia/",
    "source": "The Diplomat",
    "category": "Geopolitics",
    "published": "Tue, 23 Dec 2025 15:35:00 +0900",
    "thumbnail": "https://images.thediplomat.com/v1/td-list-l-2/2025/12/thediplomat_2025-12-23-153944.jpg",
    "importance": 25,
    "importanceLabel": "Low",
    "updated_at": "2025-12-24T02:54:56.621211"
  },
  {
    "title": "Does Australia Need Additional Hate Speech Laws?",
    "link": "https://thediplomat.com/2025/12/does-australia-need-additional-hate-speech-laws/",
    "source": "The Diplomat",
    "category": "Geopolitics",
    "published": "Tue, 23 Dec 2025 21:55:00 +0900",
    "thumbnail": "https://images.thediplomat.com/v1/td-list-l-2/2025/12/thediplomat_2025-12-23-215746.jpg",
    "importance": 25,
    "importanceLabel": "Low",
    "updated_at": "2025-12-24T02:54:56.621272"
  },
  {
    "title": "James Chin on the Shifting Political Sands in Malaysia’s Sabah State",
    "link": "https://thediplomat.com/2025/12/james-chin-on-the-shifting-political-sands-in-malaysias-sabah-state/",
    "source": "The Diplomat",
    "category": "Geopolitics",
    "published": "Tue, 23 Dec 2025 12:20:00 +0900",
    "thumbnail": "https://images.thediplomat.com/v1/td-list-l-2/2025/12/thediplomat_2025-12-23-122934.jpg",
    "importance": 25,
    "importanceLabel": "Low",
    "updated_at": "2025-12-24T02:54:56.621323"
  },
  {
    "title": "The Pacific Money Blog: 2025 Year in Review",
    "link": "https://thediplomat.com/2025/12/the-pacific-money-blog-2025-year-in-review/",
    "source": "The Diplomat",
    "category": "Geopolitics",
    "published": "Tue, 23 Dec 2025 12:31:00 +0900",
    "thumbnail": "https://images.thediplomat.com/v1/td-list-l-2/2025/01/thediplomat_2025-01-14-211830.jpg",
    "importance": 25,
    "importanceLabel": "Low",
    "updated_at": "2025-12-24T02:54:56.621341"
  },
  {
    "title": "Thailand, Cambodia Agree to Hold Ceasefire Talks on December 24",
    "link": "https://thediplomat.com/2025/12/thailand-cambodia-agree-to-hold-ceasefire-talks-on-december-24/",
    "source": "The Diplomat",
    "category": "Geopolitics",
    "published": "Tue, 23 Dec 2025 06:59:00 +0900",
    "thumbnail": "https://images.thediplomat.com/v1/td-list-l-2/2025/12/thediplomat_2025-12-23-070054.jpg",
    "importance": 25,
    "importanceLabel": "Low",
    "updated_at": "2025-12-24T02:54:56.621360"
  },
  {
    "title": "What Really Happened to Flight MH370?",
    "link": "https://thediplomat.com/2025/12/what-really-happened-to-flight-mh370/",
    "source": "The Diplomat",
    "category": "Geopolitics",
    "published": "Tue, 23 Dec 2025 09:09:00 +0900",
    "thumbnail": "https://images.thediplomat.com/v1/td-list-l-2/2025/12/thediplomat_2025-12-23-093820.jpg",
    "importance": 25,
    "importanceLabel": "Low",
    "updated_at": "2025-12-24T02:54:56.621377"
  },
  {
    "title": "Is the Bangladeshi State Incapable or Unwilling to Control Mobs?",
    "link": "https://thediplomat.com/2025/12/is-the-bangladeshi-state-incapable-or-unwilling-to-control-mobs/",
    "source": "The Diplomat",
    "category": "Geopolitics",
    "published": "Mon, 22 Dec 2025 15:22:00 +0900",
    "thumbnail": "https://images.thediplomat.com/v1/td-list-l-2/2025/12/thediplomat_2025-12-22-152553.jpg",
    "importance": 25,
    "importanceLabel": "Low",
    "updated_at": "2025-12-24T02:54:56.621462"
  },
  {
    "title": "Jeffrey Epstein was to share cell with pro-Trump pipe bomber, newly released email shows",
    "link": "https://indianexpress.com/article/world/jeffrey-epstein-was-to-share-cell-with-pro-trump-pipe-bomber-newly-released-email-shows-10435674/",
    "source": "World | The Indian Express",
    "category": "Geopolitics",
    "published": "Tue, 23 Dec 2025 19:20:09 +0000",
    "thumbnail": "https://images.indianexpress.com/2025/12/Epstein.jpg",
    "importance": 25,
    "importanceLabel": "Low",
    "updated_at": "2025-12-24T02:54:57.045873"
  },
  {
    "title": "Jeffrey Epstein victim who voted for Donald Trump says she ‘would love’ to see him impeached",
    "link": "https://indianexpress.com/article/world/jeffrey-epstein-victim-who-voted-for-donald-trump-says-she-would-love-to-see-him-impeached-10435629/",
    "source": "World | The Indian Express",
    "category": "Geopolitics",
    "published": "Tue, 23 Dec 2025 18:14:09 +0000",
    "thumbnail": "https://images.indianexpress.com/2025/12/epstein-survivors-capitol-03-rt-jef-250903_1756913060985_hpMain-1.jpg",
    "importance": 25,
    "importanceLabel": "Low",
    "updated_at": "2025-12-24T02:54:57.045928"
  },
  {
    "title": "PM Shehbaz offers talks to Imran Khan’s party to ease political tension",
    "link": "https://indianexpress.com/article/world/pm-shehbaz-offers-talks-to-imran-khan-pti-to-ease-political-tension-10435610/",
    "source": "World | The Indian Express",
    "category": "Geopolitics",
    "published": "Tue, 23 Dec 2025 17:29:46 +0000",
    "thumbnail": "https://images.indianexpress.com/2025/12/YJSPC5DILJPILCIS7HGMPWCMRA-1.jpg",
    "importance": 25,
    "importanceLabel": "Low",
    "updated_at": "2025-12-24T02:54:57.045951"
  },
  {
    "title": "Bangladesh government’s representative meets family of Hindu man lynched by mob",
    "link": "https://indianexpress.com/article/world/bangladesh-governments-representative-meets-family-of-hindu-man-lynched-by-mob-10435497/",
    "source": "World | The Indian Express",
    "category": "Geopolitics",
    "published": "Tue, 23 Dec 2025 16:30:32 +0000",
    "thumbnail": "https://images.indianexpress.com/2025/12/Bangladesh-Hindu-man.jpg",
    "importance": 25,
    "importanceLabel": "Low",
    "updated_at": "2025-12-24T02:54:57.046016"
  },
  {
    "title": "Two men found guilty of UK plot to kill hundreds of Jews as IS fears grow",
    "link": "https://indianexpress.com/article/world/two-men-found-guilty-uk-plot-to-kill-hundreds-of-jews-is-fears-grow-10435473/",
    "source": "World | The Indian Express",
    "category": "Geopolitics",
    "published": "Tue, 23 Dec 2025 15:50:49 +0000",
    "thumbnail": "https://images.indianexpress.com/2025/12/uk-attack.jpg",
    "importance": 25,
    "importanceLabel": "Low",
    "updated_at": "2025-12-24T02:54:57.046033"
  },
  {
    "title": "Who was ‘Adam the Woo’? Pioneering YouTube vlogger dies at 51?",
    "link": "https://indianexpress.com/article/world/who-was-adam-the-woo-pioneering-youtube-vlogger-dies-at-51-10435417/",
    "source": "World | The Indian Express",
    "category": "Geopolitics",
    "published": "Tue, 23 Dec 2025 15:32:59 +0000",
    "thumbnail": "https://images.indianexpress.com/2025/12/adam-woo.jpg",
    "importance": 25,
    "importanceLabel": "Low",
    "updated_at": "2025-12-24T02:54:57.046054"
  },
  {
    "title": "US economy expands at a surprisingly strong 4.3% annual rate in the third quarter",
    "link": "https://indianexpress.com/article/world/us-economy-expands-strongly-in-third-quarter-10435394/",
    "source": "World | The Indian Express",
    "category": "Geopolitics",
    "published": "Tue, 23 Dec 2025 14:51:42 +0000",
    "thumbnail": "https://images.indianexpress.com/2025/12/us-Economy.jpg",
    "importance": 25,
    "importanceLabel": "Low",
    "updated_at": "2025-12-24T02:54:57.046074"
  },
  {
    "title": "Jeffrey Epstein Files: What third batch of 30,000 pages of documents revealed",
    "link": "https://indianexpress.com/article/world/what-third-batch-of-jeffrey-epstein-documents-say-10435295/",
    "source": "World | The Indian Express",
    "category": "Geopolitics",
    "published": "Tue, 23 Dec 2025 14:14:35 +0000",
    "thumbnail": "https://images.indianexpress.com/2025/12/Justice_Department_Jeffrey_Epstein_33698-ecf3b-1.jpg",
    "importance": 25,
    "importanceLabel": "Low",
    "updated_at": "2025-12-24T02:54:57.046092"
  },
  {
    "title": "‘We shared one thing’: What Jeffrey Epstein wrote to fellow sex offender Larry Nassar from jail",
    "link": "https://indianexpress.com/article/world/we-shared-one-thing-what-jeffrey-epstein-wrote-to-fellow-sex-offender-larry-nassar-from-jail-10435191/",
    "source": "World | The Indian Express",
    "category": "Geopolitics",
    "published": "Tue, 23 Dec 2025 13:32:06 +0000",
    "thumbnail": "https://images.indianexpress.com/2025/12/Justice_Department_Jeffrey_Epstein_07658-76ced-1.jpg",
    "importance": 25,
    "importanceLabel": "Low",
    "updated_at": "2025-12-24T02:54:57.046115"
  },
  {
    "title": "Epstein Files Live Updates: Epstein travelled on fake Austrian passport, files reveal, as Justice dept issues rare defence of Trump",
    "link": "https://indianexpress.com/article/world/jeffrey-epstein-files-live-updates-donald-trump-name-justice-department-10435114/",
    "source": "World | The Indian Express",
    "category": "Geopolitics",
    "published": "Tue, 23 Dec 2025 13:09:59 +0000",
    "thumbnail": "https://images.indianexpress.com/2025/12/trump-epstein-2.jpg",
    "importance": 25,
    "importanceLabel": "Low",
    "updated_at": "2025-12-24T02:54:57.046138"
  },
  {
    "title": "Greta Thunberg arrested at pro-Palestinian protest in London",
    "link": "https://indianexpress.com/article/world/greta-thunberg-arrested-at-pro-palestinian-protest-in-london-10435092/",
    "source": "World | The Indian Express",
    "category": "Geopolitics",
    "published": "Tue, 23 Dec 2025 12:14:50 +0000",
    "thumbnail": "https://images.indianexpress.com/2025/12/Greta-Thunberg.jpg",
    "importance": 25,
    "importanceLabel": "Low",
    "updated_at": "2025-12-24T02:54:57.046178"
  },
  {
    "title": "‘Trump travelled on at least 8 Epstein flights’: New batch of Epstein files released by Justice Department show",
    "link": "https://indianexpress.com/article/world/new-batch-of-epstein-files-released-justice-department-trump-name-appears-10435087/",
    "source": "World | The Indian Express",
    "category": "Geopolitics",
    "published": "Tue, 23 Dec 2025 12:10:01 +0000",
    "thumbnail": "https://images.indianexpress.com/2025/12/epstein-trump.jpg",
    "importance": 25,
    "importanceLabel": "Low",
    "updated_at": "2025-12-24T02:54:57.046202"
  },
  {
    "title": "Call of Duty co-creator Vince Zampella dies in California car crash",
    "link": "https://www.bbc.com/news/articles/cx25rled0ylo?at_medium=RSS&at_campaign=rss",
    "source": "BBC News",
    "category": "Technology",
    "published": "Tue, 23 Dec 2025 10:04:47 GMT",
    "thumbnail": "https://ichef.bbci.co.uk/ace/standard/240/cpsprodpb/09cf/live/c3c06b50-df84-11f0-b89f-11674143d4d8.jpg",
    "importance": 25,
    "importanceLabel": "Low",
    "updated_at": "2025-12-24T02:54:57.243944"
  },
  {
    "title": "India, New Zealand wrap FTA talks, aim to double trade in five years",
    "link": "https://indianexpress.com/article/business/india-new-zealand-wrap-fta-talks-aim-to-double-trade-in-five-years-10433839/",
    "source": "Business | The Indian Express",
    "category": "Business",
    "published": "Tue, 23 Dec 2025 01:45:50 +0000",
    "thumbnail": "https://images.indianexpress.com/2025/12/goods-exports_20251222205507.jpg",
    "importance": 25,
    "importanceLabel": "Low",
    "updated_at": "2025-12-24T02:54:57.620123"
  },
  {
    "title": "India-New Zealand conclude FTA talks amid continuing high US tariffs",
    "link": "https://indianexpress.com/article/business/india-new-zealand-conclude-fta-talks-amid-continuing-high-us-tariffs-10433020/",
    "source": "Business | The Indian Express",
    "category": "Business",
    "published": "Mon, 22 Dec 2025 09:29:31 +0000",
    "thumbnail": "https://images.indianexpress.com/2025/12/Photo-2025-12-22T145812.365.jpg",
    "importance": 25,
    "importanceLabel": "Low",
    "updated_at": "2025-12-24T02:54:57.620258"
  },
  {
    "title": "Air India Boeing 777 returns to Delhi after pilots spot low engine oil pressure shortly after take-off; probe ordered",
    "link": "https://indianexpress.com/article/business/aviation/air-india-boeing-777-returns-to-delhi-after-pilots-spot-low-engine-oil-pressure-shortly-after-take-off-probe-ordered-10432962/",
    "source": "Business | The Indian Express",
    "category": "Business",
    "published": "Mon, 22 Dec 2025 08:53:53 +0000",
    "thumbnail": "https://images.indianexpress.com/2025/12/air-india-b777.jpg",
    "importance": 25,
    "importanceLabel": "Low",
    "updated_at": "2025-12-24T02:54:57.620279"
  },
  {
    "title": "Global AI models don’t customise enough; India has a big opportunity: Professor Susan Athey",
    "link": "https://indianexpress.com/article/business/global-ai-models-dont-customise-enough-india-has-opportunity-susan-athey-10432041/",
    "source": "Business | The Indian Express",
    "category": "Business",
    "published": "Sun, 21 Dec 2025 16:56:22 +0000",
    "thumbnail": "https://images.indianexpress.com/2025/12/Professor-Susan-Athey-express-photo.jpg",
    "importance": 25,
    "importanceLabel": "Low",
    "updated_at": "2025-12-24T02:54:57.620321"
  },
  {
    "title": "Passenger alleges assault by Air India Express pilot at Delhi airport; govt orders probe, airline suspends pilot",
    "link": "https://indianexpress.com/article/business/aviation/air-india-express-pilot-assault-passenger-delhi-airport-10430442/",
    "source": "Business | The Indian Express",
    "category": "Business",
    "published": "Sat, 20 Dec 2025 11:19:04 +0000",
    "thumbnail": "https://images.indianexpress.com/2025/12/Air-India-Express-pilot-assaults-passenger.jpg",
    "importance": 25,
    "importanceLabel": "Low",
    "updated_at": "2025-12-24T02:54:57.620401"
  },
  {
    "title": "Japan’s MUFG Bank to invest Rs 39,000 crore in Shriram Finance for 20% stake",
    "link": "https://indianexpress.com/article/business/japans-mufg-bank-to-invest-rs-39000-crore-in-shriram-finance-for-20-stake-10429461/",
    "source": "Business | The Indian Express",
    "category": "Business",
    "published": "Fri, 19 Dec 2025 17:24:28 +0000",
    "thumbnail": "https://images.indianexpress.com/2025/12/mufg-shriram-.jpg",
    "importance": 25,
    "importanceLabel": "Low",
    "updated_at": "2025-12-24T02:54:57.620422"
  },
  {
    "title": "LVMH-backed private equity firm L Catterton picks up stake in Haldiram’s",
    "link": "https://indianexpress.com/article/business/lvmh-backed-private-equity-firm-l-catterton-haldirams-stake-10429378/",
    "source": "Business | The Indian Express",
    "category": "Business",
    "published": "Fri, 19 Dec 2025 16:24:13 +0000",
    "thumbnail": "https://images.indianexpress.com/2025/12/Haldirams.jpg",
    "importance": 25,
    "importanceLabel": "Low",
    "updated_at": "2025-12-24T02:54:57.620443"
  },
  {
    "title": "Amazon blocks 1,800 job applications from suspected North Korean agents",
    "link": "https://www.bbc.com/news/articles/c3e0kw80wwzo?at_medium=RSS&at_campaign=rss",
    "source": "BBC News",
    "category": "Technology",
    "published": "Tue, 23 Dec 2025 02:49:45 GMT",
    "thumbnail": "https://ichef.bbci.co.uk/ace/standard/240/cpsprodpb/7a77/live/f29f1a40-dfa0-11f0-a643-15fd7b194a0b.jpg",
    "importance": 20,
    "importanceLabel": "Low",
    "updated_at": "2025-12-24T02:54:57.243962"
  },
  {
    "title": "Amid rising complaints of stuck refunds, Income Tax Dept cites high ineligible claims; asks taxpayers to file revised ITRs",
    "link": "https://indianexpress.com/article/business/amid-rising-complaints-of-stuck-refunds-income-tax-dept-cites-high-ineligible-claims-asks-taxpayers-to-file-revised-itrs-10435376/",
    "source": "Business | The Indian Express",
    "category": "Business",
    "published": "Tue, 23 Dec 2025 14:50:15 +0000",
    "thumbnail": "https://images.indianexpress.com/2025/12/income-tax.jpg",
    "importance": 20,
    "importanceLabel": "Low",
    "updated_at": "2025-12-24T02:54:57.620061"
  },
  {
    "title": "RBI to inject Rs 290,000 crore liquidity via securities purchase, swap auction",
    "link": "https://indianexpress.com/article/business/rbi-to-inject-rs-290000-crore-liquidity-via-securities-purchase-swap-auction-10435342/",
    "source": "Business | The Indian Express",
    "category": "Business",
    "published": "Tue, 23 Dec 2025 14:29:54 +0000",
    "thumbnail": "https://images.indianexpress.com/2025/12/rbi-1.jpg",
    "importance": 20,
    "importanceLabel": "Low",
    "updated_at": "2025-12-24T02:54:57.620080"
  },
  {
    "title": "Continued focus on macro fundamentals, reforms to enable economy to maintain high growth: RBI’s State of The Economy article",
    "link": "https://indianexpress.com/article/business/economy/continued-focus-on-macro-fundamentals-reforms-to-enable-economy-maintain-high-growth-rbis-state-of-economy-article-10433745/",
    "source": "Business | The Indian Express",
    "category": "Business",
    "published": "Tue, 23 Dec 2025 00:25:51 +0000",
    "thumbnail": "https://images.indianexpress.com/2025/12/msme-sector-India-GDP-economy.jpg",
    "importance": 20,
    "importanceLabel": "Low",
    "updated_at": "2025-12-24T02:54:57.620152"
  },
  {
    "title": "No extension beyond March for IndiGo’s wet-leased planes from Turkey; its Turkish Airlines 777s to go back after February",
    "link": "https://indianexpress.com/article/business/aviation/no-extension-beyond-march-for-indigos-wet-leased-planes-from-turkey-its-turkish-airlines-777s-to-go-back-after-february-10433898/",
    "source": "Business | The Indian Express",
    "category": "Business",
    "published": "Mon, 22 Dec 2025 23:25:50 +0000",
    "thumbnail": "https://images.indianexpress.com/2025/12/indigo-8_20251222232248.jpg",
    "importance": 20,
    "importanceLabel": "Low",
    "updated_at": "2025-12-24T02:54:57.620178"
  },
  {
    "title": "Adani cements consolidation: ACC, Orient to merge with Ambuja Cements",
    "link": "https://indianexpress.com/article/business/companies/adani-cements-consolidation-acc-orient-to-merge-with-ambuja-cements-10433724/",
    "source": "Business | The Indian Express",
    "category": "Business",
    "published": "Mon, 22 Dec 2025 19:30:41 +0000",
    "thumbnail": "https://images.indianexpress.com/2025/12/Ambuja-Cements.jpg",
    "importance": 20,
    "importanceLabel": "Low",
    "updated_at": "2025-12-24T02:54:57.620195"
  },
  {
    "title": "Tata Electronics signs chip deal with Japan’s ROHM",
    "link": "https://indianexpress.com/article/business/electronics-signs-chip-deal-with-japan-rohm-10432750/",
    "source": "Business | The Indian Express",
    "category": "Business",
    "published": "Mon, 22 Dec 2025 07:36:14 +0000",
    "thumbnail": "https://images.indianexpress.com/2025/12/Tata-Electronics.jpg",
    "importance": 20,
    "importanceLabel": "Low",
    "updated_at": "2025-12-24T02:54:57.620298"
  },
  {
    "title": "Land bottlenecks drive CPSUs to team up with states for 33 solar parks",
    "link": "https://indianexpress.com/article/business/land-bottlenecks-drive-cpsu-states-solar-parks-10431998/",
    "source": "Business | The Indian Express",
    "category": "Business",
    "published": "Sun, 21 Dec 2025 16:26:23 +0000",
    "thumbnail": "https://images.indianexpress.com/2025/12/Solar-Park.jpg",
    "importance": 20,
    "importanceLabel": "Low",
    "updated_at": "2025-12-24T02:54:57.620339"
  },
  {
    "title": "In 6 months, Railways hikes passenger fares again across classes; suburban ticket rates unchanged",
    "link": "https://indianexpress.com/article/business/in-6-months-railways-hikes-passenger-fares-again-across-classes-suburban-ticket-rates-unchanged-10431649/",
    "source": "Business | The Indian Express",
    "category": "Business",
    "published": "Sun, 21 Dec 2025 10:33:19 +0000",
    "thumbnail": "https://images.indianexpress.com/2025/12/train-1-1.jpg",
    "importance": 20,
    "importanceLabel": "Low",
    "updated_at": "2025-12-24T02:54:57.620358"
  },
  {
    "title": "US denies visas to ex-EU commissioner and others over social media rules",
    "link": "https://www.bbc.com/news/articles/cp39kngz008o?at_medium=RSS&at_campaign=rss",
    "source": "BBC News",
    "category": "Technology",
    "published": "Wed, 24 Dec 2025 00:45:28 GMT",
    "thumbnail": "https://ichef.bbci.co.uk/ace/standard/240/cpsprodpb/1292/live/5259b830-e05c-11f0-bdd6-e11ea3d501a5.jpg",
    "importance": 15,
    "importanceLabel": "Low",
    "updated_at": "2025-12-24T02:54:57.243899"
  },
  {
    "title": "TikTok removes AI weight loss ads from fake Boots account",
    "link": "https://www.bbc.com/news/articles/c997lkdjdy5o?at_medium=RSS&at_campaign=rss",
    "source": "BBC News",
    "category": "Technology",
    "published": "Tue, 23 Dec 2025 09:23:51 GMT",
    "thumbnail": "https://ichef.bbci.co.uk/ace/standard/240/cpsprodpb/4611/live/67ea27b0-dd01-11f0-b67b-690eb873de1b.jpg",
    "importance": 15,
    "importanceLabel": "Low",
    "updated_at": "2025-12-24T02:54:57.243925"
  },
  {
    "title": "Uber and Lyft announce plans to trial Chinese robotaxis in UK in 2026",
    "link": "https://www.bbc.com/news/articles/cy8jmx1dl9ro?at_medium=RSS&at_campaign=rss",
    "source": "BBC News",
    "category": "Technology",
    "published": "Mon, 22 Dec 2025 14:08:48 GMT",
    "thumbnail": "https://ichef.bbci.co.uk/ace/standard/240/cpsprodpb/7a81/live/5050e1a0-df24-11f0-9dac-b79514ec4a2d.jpg",
    "importance": 15,
    "importanceLabel": "Low",
    "updated_at": "2025-12-24T02:54:57.243979"
  },
  {
    "title": "Will the US TikTok deal make it safer but less relevant?",
    "link": "https://www.bbc.com/news/articles/clydp2ygrveo?at_medium=RSS&at_campaign=rss",
    "source": "BBC News",
    "category": "Technology",
    "published": "Fri, 19 Dec 2025 13:45:50 GMT",
    "thumbnail": "https://ichef.bbci.co.uk/ace/standard/240/cpsprodpb/c377/live/a166ca10-dca8-11f0-bf97-a767b375b25e.jpg",
    "importance": 15,
    "importanceLabel": "Low",
    "updated_at": "2025-12-24T02:54:57.243995"
  },
  {
    "title": "TikTok owner signs deal to avoid US ban",
    "link": "https://www.bbc.com/news/articles/cgexp1q8wn1o?at_medium=RSS&at_campaign=rss",
    "source": "BBC News",
    "category": "Technology",
    "published": "Fri, 19 Dec 2025 07:27:18 GMT",
    "thumbnail": "https://ichef.bbci.co.uk/ace/standard/240/cpsprodpb/da55/live/b4d55230-dcf6-11f0-b67b-690eb873de1b.jpg",
    "importance": 15,
    "importanceLabel": "Low",
    "updated_at": "2025-12-24T02:54:57.244011"
  },
  {
    "title": "UK to ban deepfake AI 'nudification' apps",
    "link": "https://www.bbc.com/news/articles/cq8dp2y0z7wo?at_medium=RSS&at_campaign=rss",
    "source": "BBC News",
    "category": "Technology",
    "published": "Thu, 18 Dec 2025 17:43:14 GMT",
    "thumbnail": "https://ichef.bbci.co.uk/ace/standard/240/cpsprodpb/3266/live/44191530-dc34-11f0-a665-27b3eb61cb96.jpg",
    "importance": 15,
    "importanceLabel": "Low",
    "updated_at": "2025-12-24T02:54:57.244026"
  },
  {
    "title": "£100 contactless card limit to be lifted",
    "link": "https://www.bbc.com/news/articles/cx2prjr4lpko?at_medium=RSS&at_campaign=rss",
    "source": "BBC News",
    "category": "Technology",
    "published": "Fri, 19 Dec 2025 15:59:19 GMT",
    "thumbnail": "https://ichef.bbci.co.uk/ace/standard/240/cpsprodpb/0454/live/c3c35f10-dcf3-11f0-b67b-690eb873de1b.jpg",
    "importance": 15,
    "importanceLabel": "Low",
    "updated_at": "2025-12-24T02:54:57.244043"
  },
  {
    "title": "One in three using AI for emotional support and conversation, UK says",
    "link": "https://www.bbc.com/news/articles/cd6xl3ql3v0o?at_medium=RSS&at_campaign=rss",
    "source": "BBC News",
    "category": "Technology",
    "published": "Thu, 18 Dec 2025 12:37:46 GMT",
    "thumbnail": "https://ichef.bbci.co.uk/ace/standard/240/cpsprodpb/a78c/live/410e01b0-db7c-11f0-b5d0-e9a8f87cff6a.jpg",
    "importance": 15,
    "importanceLabel": "Low",
    "updated_at": "2025-12-24T02:54:57.244061"
  },
  {
    "title": "Facebook tests £9.99 monthly subscription for sharing more than two links",
    "link": "https://www.bbc.com/news/articles/cp9kv3lezgro?at_medium=RSS&at_campaign=rss",
    "source": "BBC News",
    "category": "Technology",
    "published": "Thu, 18 Dec 2025 12:13:14 GMT",
    "thumbnail": "https://ichef.bbci.co.uk/ace/standard/240/cpsprodpb/06f0/live/386166e0-dc05-11f0-932f-e1ac58e2c593.jpg",
    "importance": 15,
    "importanceLabel": "Low",
    "updated_at": "2025-12-24T02:54:57.244079"
  },
  {
    "title": "Parents told to lead by example and turn off phones this Christmas",
    "link": "https://www.bbc.com/news/articles/c1dz9nnp52eo?at_medium=RSS&at_campaign=rss",
    "source": "BBC News",
    "category": "Technology",
    "published": "Thu, 18 Dec 2025 02:28:22 GMT",
    "thumbnail": "https://ichef.bbci.co.uk/ace/standard/240/cpsprodpb/a7a2/live/d642d660-db4b-11f0-bbf2-4d416c468f30.jpg",
    "importance": 15,
    "importanceLabel": "Low",
    "updated_at": "2025-12-24T02:54:57.244096"
  },
  {
    "title": "Fifa video game to return after four years in Netflix exclusive",
    "link": "https://www.bbc.com/news/articles/c93w7dp42z2o?at_medium=RSS&at_campaign=rss",
    "source": "BBC News",
    "category": "Technology",
    "published": "Wed, 17 Dec 2025 18:20:44 GMT",
    "thumbnail": "https://ichef.bbci.co.uk/ace/standard/240/cpsprodpb/931c/live/11f12bc0-db75-11f0-b5d0-e9a8f87cff6a.jpg",
    "importance": 15,
    "importanceLabel": "Low",
    "updated_at": "2025-12-24T02:54:57.244112"
  },
  {
    "title": "Downing Street insists negotiations over US-UK tech deal still live",
    "link": "https://www.bbc.com/news/articles/c79x54dprngo?at_medium=RSS&at_campaign=rss",
    "source": "BBC News",
    "category": "Technology",
    "published": "Tue, 16 Dec 2025 22:39:14 GMT",
    "thumbnail": "https://ichef.bbci.co.uk/ace/standard/240/cpsprodpb/b07a/live/9a15a890-da68-11f0-a03c-01668bc4a165.jpg",
    "importance": 15,
    "importanceLabel": "Low",
    "updated_at": "2025-12-24T02:54:57.244130"
  },
  {
    "title": "UK launches taskforce to 'break down barriers' for women in technology",
    "link": "https://www.bbc.com/news/articles/cg7vez25ly5o?at_medium=RSS&at_campaign=rss",
    "source": "BBC News",
    "category": "Technology",
    "published": "Tue, 16 Dec 2025 00:04:18 GMT",
    "thumbnail": "https://ichef.bbci.co.uk/ace/standard/240/cpsprodpb/ff57/live/f38ab2a0-d9d5-11f0-ba85-09c2975a5393.jpg",
    "importance": 15,
    "importanceLabel": "Low",
    "updated_at": "2025-12-24T02:54:57.244146"
  },
  {
    "title": "Amazon apologises after showing 15-rated film to child who rented PG movie",
    "link": "https://www.bbc.com/news/articles/cy4xwv7vdmdo?at_medium=RSS&at_campaign=rss",
    "source": "BBC News",
    "category": "Technology",
    "published": "Mon, 15 Dec 2025 13:52:12 GMT",
    "thumbnail": "https://ichef.bbci.co.uk/ace/standard/240/cpsprodpb/2c15/live/11ab6df0-d9b9-11f0-b051-c9966e31459d.jpg",
    "importance": 15,
    "importanceLabel": "Low",
    "updated_at": "2025-12-24T02:54:57.244163"
  },
  {
    "title": "Ofcom investigates BT and Three for failing to connect 999 calls",
    "link": "https://www.bbc.com/news/articles/c5y2kgdq6r3o?at_medium=RSS&at_campaign=rss",
    "source": "BBC News",
    "category": "Technology",
    "published": "Mon, 15 Dec 2025 11:41:43 GMT",
    "thumbnail": "https://ichef.bbci.co.uk/ace/standard/240/cpsprodpb/98b2/live/e1d45540-d99c-11f0-9980-0198ec088b58.jpg",
    "importance": 15,
    "importanceLabel": "Low",
    "updated_at": "2025-12-24T02:54:57.244180"
  },
  {
    "title": "Roomba vacuum cleaner firm files for bankruptcy",
    "link": "https://www.bbc.com/news/articles/c1lr75lp239o?at_medium=RSS&at_campaign=rss",
    "source": "BBC News",
    "category": "Technology",
    "published": "Mon, 15 Dec 2025 07:47:31 GMT",
    "thumbnail": "https://ichef.bbci.co.uk/ace/standard/240/cpsprodpb/beb0/live/0abd32f0-d9a8-11f0-a8dc-93c15fe68710.jpg",
    "importance": 15,
    "importanceLabel": "Low",
    "updated_at": "2025-12-24T02:54:57.244195"
  },
  {
    "title": "Grand Theft Auto game creator sacked us for trying to unionise",
    "link": "https://www.bbc.com/news/articles/cp89990rgdno?at_medium=RSS&at_campaign=rss",
    "source": "BBC News",
    "category": "Technology",
    "published": "Mon, 15 Dec 2025 10:21:43 GMT",
    "thumbnail": "https://ichef.bbci.co.uk/ace/standard/240/cpsprodpb/34f6/live/bfc01070-d77b-11f0-aae2-2191c0e48a3b.jpg",
    "importance": 15,
    "importanceLabel": "Low",
    "updated_at": "2025-12-24T02:54:57.244212"
  },
  {
    "title": "What's next for TikTok in the US as deal prospects remain uncertain?",
    "link": "https://www.bbc.com/news/articles/cp34442z25ko?at_medium=RSS&at_campaign=rss",
    "source": "BBC News",
    "category": "Technology",
    "published": "Mon, 15 Dec 2025 17:06:41 GMT",
    "thumbnail": "https://ichef.bbci.co.uk/ace/standard/240/cpsprodpb/2134/live/3e8e0eb0-d778-11f0-825e-eb4c8fb7e95e.jpg",
    "importance": 15,
    "importanceLabel": "Low",
    "updated_at": "2025-12-24T02:54:57.244229"
  }
]